sha3.v
//======================================================================
// sha3
// ----
// keccak, SHA-3 winner
// derived from "readable keccak"
// 19-Nov-11  Markku-Juhani O. Saarinen <mjos@iki.fi>
// A baseline Keccak (3rd round) implementation.
// Verilog implementation (c) 2015 by Bernd Paysan
// Ported to Cryptech Alpha platform by Pavel Shatov
//
// Redistribution and use in source and binary forms, with or without
// modification, are permitted provided that the following conditions are
// met:
// - Redistributions of source code must retain the above copyright notice,
//   this list of conditions and the following disclaimer.
//
// - Redistributions in binary form must reproduce the above copyright
//   notice, this list of conditions and the following disclaimer in the
//   documentation and/or other materials provided with the distribution.
//
// - Neither the name of the NORDUnet nor the names of its contributors may
//   be used to endorse or promote products derived from this software
//   without specific prior written permission.
//
// THIS SOFTWARE IS PROVIDED BY THE COPYRIGHT HOLDERS AND CONTRIBUTORS "AS
// IS" AND ANY EXPRESS OR IMPLIED WARRANTIES, INCLUDING, BUT NOT LIMITED
// TO, THE IMPLIED WARRANTIES OF MERCHANTABILITY AND FITNESS FOR A
// PARTICULAR PURPOSE ARE DISCLAIMED. IN NO EVENT SHALL THE COPYRIGHT
// HOLDER OR CONTRIBUTORS BE LIABLE FOR ANY DIRECT, INDIRECT, INCIDENTAL,
// SPECIAL, EXEMPLARY, OR CONSEQUENTIAL DAMAGES (INCLUDING, BUT NOT LIMITED
// TO, PROCUREMENT OF SUBSTITUTE GOODS OR SERVICES; LOSS OF USE, DATA, OR
// PROFITS; OR BUSINESS INTERRUPTION) HOWEVER CAUSED AND ON ANY THEORY OF
// LIABILITY, WHETHER IN CONTRACT, STRICT LIABILITY, OR TORT (INCLUDING
// NEGLIGENCE OR OTHERWISE) ARISING IN ANY WAY OUT OF THE USE OF THIS
// SOFTWARE, EVEN IF ADVISED OF THE POSSIBILITY OF SUCH DAMAGE.
//
//======================================================================

`define rotl64(x, r) ((({x, x}<<r)>>64)& 64'hffffffffffffffff)
`define rotci(i) ((rotc>>((23-i)*6)) & 6'h3f)
`define pilni(i) ((piln>>((23-i)*5)) & 5'h1f)
`define rndci(i) ((rndc>>((23-i)*64)) & 64'hffffffffffffffff)

`define SHA3_NUM_ROUNDS         5'd24
/* verilator lint_off WIDTH */
module sha3(    input wire          clk,
                input wire 	     nreset,
                input wire 	     w,
                input wire [ 8:2]    addr,
                input wire [32-1:0]  din,
                output wire [32-1:0] dout,
                input wire 	     init,
                input wire 	     next,
                output wire 	     ready);


   /*
    * The SHA-3 algorithm really wants everything to be little-endian,
    * which is at odds with everything else in our system (including the
    * register interface to sha3_wrapper). Rather than trying to rewrite
    * Bernd's beautiful code, I'll isolate it in its own little-endian
    * universe by byte-swapping all reads and writes.
    */

   reg [31:0]                       dout_swap;
   //assign dout = {dout_swap[7:0], dout_swap[15:8], dout_swap[23:16], dout_swap[31:24]};
   assign dout = dout_swap;

   wire [31:0]                      din_swap;
   //assign din_swap = {din[7:0], din[15:8], din[23:16], din[31:24]};
    assign din_swap = din;

   integer                          i, j;

   reg [64-1:0]                     blk[0:24],  // input block
                                    st [0:24],  // current state
                                    stn[0:24],  // new state
                                    bc [0: 4],  // intermediate values
                                    t;          // temporary variable

   reg [   4:0]                     round;      // counter value


   localparam   [ 4: 0] roundlimit = `SHA3_NUM_ROUNDS - 'b1;


   localparam   [24*6-1:0]      rotc =
                                      { 6'h01, 6'h03, 6'h06, 6'h0A, 6'h0F, 6'h15,
                                        6'h1C, 6'h24, 6'h2D, 6'h37, 6'h02, 6'h0E,
                                        6'h1B, 6'h29, 6'h38, 6'h08, 6'h19, 6'h2B,
                                        6'h3E, 6'h12, 6'h27, 6'h3D, 6'h14, 6'h2C};

   localparam   [24*5-1:0]      piln =
                                      { 5'h0A, 5'h07, 5'h0B, 5'h11, 5'h12, 5'h03,
                                        5'h05, 5'h10, 5'h08, 5'h15, 5'h18, 5'h04,
                                        5'h0F, 5'h17, 5'h13, 5'h0D, 5'h0C, 5'h02,
                                        5'h14, 5'h0E, 5'h16, 5'h09, 5'h06, 5'h01};

   localparam   [24*64-1:0]     rndc =
                                      { 64'h0000000000000001, 64'h0000000000008082,
                                        64'h800000000000808a, 64'h8000000080008000,
                                        64'h000000000000808b, 64'h0000000080000001,
                                        64'h8000000080008081, 64'h8000000000008009,
                                        64'h000000000000008a, 64'h0000000000000088,
                                        64'h0000000080008009, 64'h000000008000000a,
                                        64'h000000008000808b, 64'h800000000000008b,
                                        64'h8000000000008089, 64'h8000000000008003,
                                        64'h8000000000008002, 64'h8000000000000080,
                                        64'h000000000000800a, 64'h800000008000000a,
                                        64'h8000000080008081, 64'h8000000000008080,
                                        64'h0000000080000001, 64'h8000000080008008};

   /* input block buffer is mapped to the lower half of the
    address space, sponge state is mapped to the upper one */

   /* the lowest address bit determines what part of 64-bit word to return */

   always @*
     //
     dout_swap = addr[8] ?
                 (~addr[2] ? st [addr[7:3]][31:0] : st [addr[7:3]][63:32]) :
                 (~addr[2] ? blk[addr[7:3]][31:0] : blk[addr[7:3]][63:32]) ;


   always @* begin

      // theta1
      for (i=0; i<25; i=i+1)
        stn[i] = st[i];

      for (i=0; i<5; i=i+1)
        bc[i] = stn[i] ^ stn[i+5] ^ stn[i+10] ^ stn[i+15] ^ stn[i+20];

      // theta2
      for (i=0; i<5; i=i+1) begin

         t = bc[(i+4)%5] ^ `rotl64(bc[(i+1)%5], 1);

         for(j=i; j<25; j=j+5)
           stn[j] = t ^ stn[j];
      end

      // rophi
      t = stn[1];
      for(i=0; i<24; i=i+1) begin
         j = `pilni(i);
         { stn[j], t } = { `rotl64(t, `rotci(i)), stn[j] };
      end

      // chi
      for (j=0; j<25; j=j+5) begin

         for (i=0; i<5; i=i+1)
           bc[i] = stn[j + i];

         for (i=0; i<5; i=i+1)
           stn[j+i] = stn[j+i] ^ (~bc[(i+1)%5] & bc[(i+2)%5]);
      end

      // iota
      stn[0] = stn[0] ^ `rndci(round);
   end


   /* ready flag logic */

   reg  ready_reg = 'b1;
   assign ready = ready_reg;

   always @(posedge clk or negedge nreset)
     //
     if (!nreset)       ready_reg <= 'b1;
     else begin
        if (ready)      ready_reg <= !(init || next);
        else            ready_reg <= !(round < roundlimit);
     end

   /* state update logic */
   always @(posedge clk or negedge nreset)
     //
     if (!nreset) begin

        for (i=0; i<25; i=i+1) begin
           st[i]        <= 64'hX;       // wipe state
           blk[i]       <= 64'h0;       // wipe block
        end

        round           <= `SHA3_NUM_ROUNDS;

     end else begin

        if (!ready) begin

           for (i=0; i<25; i=i+1)
             st[i] <= stn[i];

           round <= round + 'd1;

        end else if (init || next) begin

           for (i=0; i<25; i=i+1)
             st[i] <= init ? blk[i] : st[i] ^ blk[i];   // init has priority over next

           round <= 'd0;

        end

        if (w)
          //
          case (addr[2])
            1: blk[addr[7:3]][63:32] <= din_swap;
            0: blk[addr[7:3]][31: 0] <= din_swap;
          endcase

     end


endmodule // sha3
/* verilator lint_on WIDTH */
//======================================================================

SHAKE_wrapper.sv
module SHAKE_wrapper(
    input        clk,
    input        rst_n,
    input [31:0] seed_buffer,
    input [7:0]  absorb_num,//一共需要吸收的块的数量
    input [5:0]  last_block_bytes,//最后一块数据的字节数
    input        init,
    input        mode, // 0 for SHAKE128, 1 for SHAKE256

    output [31:0] dout,
    output logic [31:0] addr_seed,
    output       ready,
    output       valid 
    );

    logic [2:0] state,next_state;
    logic nreset;
    logic [5:0] cnt_absorb_once;
    logic [7:0] cnt_absorb_total;
    logic PADDING_FLAG1,PADDING_FLAG2,PADDING_FLAG3;
    logic wr_keccak;
    logic absorb_done;
    logic [31:0] din;
    logic [7:0] addr_keccak;
    logic [7:0] ABSORB_TOTAL_CNT;
    logic [5:0] ABSORB_ONCE_CNT;
    logic [2:0] last_state;
    assign ABSORB_TOTAL_CNT = absorb_num;
    assign ABSORB_ONCE_CNT = (mode==1'b0)?6'd43:6'd34;
    // FSM ctrl
    parameter IDLE = 3'b000,
               INIT = 3'b001,
               ABSORB = 3'b010,
               SQUEEZING = 3'b011;


    always_comb begin
        case(state)
            IDLE: begin
                if(init) next_state = INIT;
                else next_state = IDLE;
            end
            INIT: begin
                next_state = ABSORB;
            end
            ABSORB: begin
                if(absorb_done) next_state = SQUEEZING;
                else next_state = ABSORB;
            end
            SQUEEZING: begin
                next_state = SQUEEZING;
            end
            default: next_state = IDLE;
        endcase
    end

    always_ff@(posedge clk or negedge rst_n)begin
        if(!rst_n)begin
            state <= 3'b0;
            last_state <= 3'b0;
        end
        else begin
            last_state <= state;
            state<=next_state;
        end
    end



    always_ff @(posedge clk or negedge rst_n) begin:counter_of_absorbing
        if(!rst_n) begin
            cnt_absorb_once <= 6'd0;
            cnt_absorb_total <= 8'd0;
            absorb_done <= 1'b0;
        end
        else begin
            if(next_state==ABSORB && state==INIT)begin
                cnt_absorb_once <= 6'd0;
                cnt_absorb_total <= 8'd0;
                absorb_done <= 1'b0;
                if(absorb_num<2) PADDING_FLAG1 <= 1'b1;
                else PADDING_FLAG1 <= 1'b0;

            end else if(state==ABSORB && ready)begin
                if(cnt_absorb_once < ABSORB_ONCE_CNT - 1) begin
                    cnt_absorb_once <= cnt_absorb_once + 6'd1;
                    if(PADDING_FLAG1==1'b1 && cnt_absorb_once == {2'b00,last_block_bytes[5:2]}-1) begin
                        PADDING_FLAG2 <= 1'b1;
                    end
                    init_keccak <= 1'b0;
                end
                else begin
                    cnt_absorb_once <= 6'd0;
                    init_keccak <= 1'b1;
                    if(cnt_absorb_total < ABSORB_TOTAL_CNT)begin
                        cnt_absorb_total <= cnt_absorb_total + 8'd1;
                        if(cnt_absorb_total == absorb_num - 2) begin
                            PADDING_FLAG1 <= 1'b1;
                        end
                        if(cnt_absorb_total == ABSORB_TOTAL_CNT -1) begin
                            absorb_done <= 1'b1;
                        end
                    end
                    else begin 
                        cnt_absorb_total <= cnt_absorb_total;
                    end
                end
            end else if (!ready)begin
                cnt_absorb_once <= 6'd0;
            end
        end
        end

    always_ff @(posedge clk or negedge rst_n) begin:absorb_addr
        if(!rst_n) begin
            addr_seed <= 32'd0;
            wr_keccak <= 1'b0;
            addr_keccak <= 8'd0;
        end
        else begin
            if(last_state!=ABSORB) begin
                addr_seed <= 32'd0;
            end
            else begin
                addr_seed <= addr_seed + 32'd4;
            end
            if(last_state!=ABSORB||!ready) begin
                addr_keccak <= 8'd0;
            end
            else begin
                addr_keccak <= addr_keccak + 8'd4;
            end
            if(state!=ABSORB) begin
                wr_keccak <= 1'b0;
            end
            else begin
                wr_keccak <= 1'b1;
            end
        end
    end
    
    always_ff @(posedge clk or negedge rst_n) begin
        if(!rst_n) begin
            din <= 32'd0;
            PADDING_FLAG3 <= 1'b0;
        end
        else begin
            if(state==ABSORB && ready) begin
                if(!PADDING_FLAG1 && !PADDING_FLAG2) begin
                    din <= seed_buffer;
                end
                else if(PADDING_FLAG2&&!PADDING_FLAG3) begin
                    case(last_block_bytes[1:0])
                        2'b00: din <= 32'h0000001F;
                        2'b11: din <={8'h1F,seed_buffer[23:0]};
                        2'b10: din <={16'h001F,seed_buffer[15:0]};
                        2'b01: din <={24'h00001F,seed_buffer[7:0]};
                        default: din <= 32'd0;
                    endcase
                    PADDING_FLAG3 <= 1'b1;
                end
                else begin
                    if(PADDING_FLAG3)begin
                        if(cnt_absorb_once == ABSORB_ONCE_CNT - 2)
                        din<=32'h80000000;
                        else
                        din<=32'h00000000;
                    end else din<=seed_buffer;
                end
            end
            else begin
                
            end
        end
    end

// nreset control
    always_ff@(posedge clk or negedge rst_n) begin
        if(!rst_n) begin
            nreset <= 1'b0;
        end
        else begin
            if(state==INIT)begin
                nreset <= 1'b0;
            end
            else begin
                nreset <= 1'b1;
            end
        end
    end

// interface with sha3
logic init_keccak,next,init_keccak_trig;
logic [6:0] comp_addr_keccak;
assign comp_addr_keccak = {1'b0,addr_keccak[7:2]};
        sha3 u_sha3(
             .clk    	(clk     ),
             .nreset 	(nreset  ),
             .w      	(wr_keccak ),
             .addr   	(comp_addr_keccak    ),
             .din    	(din     ),
             .dout   	(dout    ),
             .init   	(init_keccak    ),
             .next   	(next    ),
             .ready  	(ready   )
         );
    rise_trigger u_rise_trigger(
        .clk(clk),
        .in_sig(init_keccak),
        .out_sig(init_keccak_trig)
    );
endmodule


module rise_trigger(
    input clk,
    input in_sig,
    output logic out_sig
    );
    logic in_sig_dly;
    always_ff@(posedge clk) begin
        in_sig_dly <= in_sig;
        out_sig <= in_sig & ~in_sig_dly;
    end
endmodule

waveform.vcd
$version Generated by VerilatedVcd $end
$timescale 1ps $end
 $scope module TOP $end
  $var wire 1 x! clk $end
  $var wire 1 y! rst_n $end
  $var wire 32 z! seed_buffer [31:0] $end
  $var wire 8 {! absorb_num [7:0] $end
  $var wire 6 |! last_block_bytes [5:0] $end
  $var wire 1 }! init $end
  $var wire 1 ~! mode $end
  $var wire 32 !" dout [31:0] $end
  $var wire 32 "" addr_seed [31:0] $end
  $var wire 1 #" ready $end
  $var wire 1 $" valid $end
  $scope module SHAKE_wrapper $end
   $var wire 1 x! clk $end
   $var wire 1 y! rst_n $end
   $var wire 32 z! seed_buffer [31:0] $end
   $var wire 8 {! absorb_num [7:0] $end
   $var wire 6 |! last_block_bytes [5:0] $end
   $var wire 1 }! init $end
   $var wire 1 ~! mode $end
   $var wire 32 !" dout [31:0] $end
   $var wire 32 "" addr_seed [31:0] $end
   $var wire 1 #" ready $end
   $var wire 1 $" valid $end
   $var wire 3 k! state [2:0] $end
   $var wire 3 %" next_state [2:0] $end
   $var wire 1 l! nreset $end
   $var wire 6 m! cnt_absorb_once [5:0] $end
   $var wire 8 n! cnt_absorb_total [7:0] $end
   $var wire 1 o! PADDING_FLAG1 $end
   $var wire 1 p! PADDING_FLAG2 $end
   $var wire 1 q! PADDING_FLAG3 $end
   $var wire 1 r! wr_keccak $end
   $var wire 1 s! absorb_done $end
   $var wire 32 t! din [31:0] $end
   $var wire 8 u! addr_keccak [7:0] $end
   $var wire 8 {! ABSORB_TOTAL_CNT [7:0] $end
   $var wire 6 &" ABSORB_ONCE_CNT [5:0] $end
   $var wire 3 '" last_state [2:0] $end
   $var wire 3 +" IDLE [2:0] $end
   $var wire 3 ," INIT [2:0] $end
   $var wire 3 -" ABSORB [2:0] $end
   $var wire 3 ." SQUEEZING [2:0] $end
   $var wire 1 v! init_keccak $end
   $var wire 1 /" next $end
   $var wire 1 (" init_keccak_trig $end
   $var wire 7 w! comp_addr_keccak [6:0] $end
   $scope module u_rise_trigger $end
    $var wire 1 x! clk $end
    $var wire 1 v! in_sig $end
    $var wire 1 (" out_sig $end
    $var wire 1 )" in_sig_dly $end
   $upscope $end
   $scope module u_sha3 $end
    $var wire 1 x! clk $end
    $var wire 1 l! nreset $end
    $var wire 1 r! w $end
    $var wire 7 w! addr [8:2] $end
    $var wire 32 t! din [31:0] $end
    $var wire 32 !" dout [31:0] $end
    $var wire 1 v! init $end
    $var wire 1 /" next $end
    $var wire 1 #" ready $end
    $var wire 32 *" dout_swap [31:0] $end
    $var wire 32 t! din_swap [31:0] $end
    $var wire 32 # i [31:0] $end
    $var wire 32 $ j [31:0] $end
    $var wire 64 % blk[0] [63:0] $end
    $var wire 64 ' blk[1] [63:0] $end
    $var wire 64 ) blk[2] [63:0] $end
    $var wire 64 + blk[3] [63:0] $end
    $var wire 64 - blk[4] [63:0] $end
    $var wire 64 / blk[5] [63:0] $end
    $var wire 64 1 blk[6] [63:0] $end
    $var wire 64 3 blk[7] [63:0] $end
    $var wire 64 5 blk[8] [63:0] $end
    $var wire 64 7 blk[9] [63:0] $end
    $var wire 64 9 blk[10] [63:0] $end
    $var wire 64 ; blk[11] [63:0] $end
    $var wire 64 = blk[12] [63:0] $end
    $var wire 64 ? blk[13] [63:0] $end
    $var wire 64 A blk[14] [63:0] $end
    $var wire 64 C blk[15] [63:0] $end
    $var wire 64 E blk[16] [63:0] $end
    $var wire 64 G blk[17] [63:0] $end
    $var wire 64 I blk[18] [63:0] $end
    $var wire 64 K blk[19] [63:0] $end
    $var wire 64 M blk[20] [63:0] $end
    $var wire 64 O blk[21] [63:0] $end
    $var wire 64 Q blk[22] [63:0] $end
    $var wire 64 S blk[23] [63:0] $end
    $var wire 64 U blk[24] [63:0] $end
    $var wire 64 W st[0] [63:0] $end
    $var wire 64 Y st[1] [63:0] $end
    $var wire 64 [ st[2] [63:0] $end
    $var wire 64 ] st[3] [63:0] $end
    $var wire 64 _ st[4] [63:0] $end
    $var wire 64 a st[5] [63:0] $end
    $var wire 64 c st[6] [63:0] $end
    $var wire 64 e st[7] [63:0] $end
    $var wire 64 g st[8] [63:0] $end
    $var wire 64 i st[9] [63:0] $end
    $var wire 64 k st[10] [63:0] $end
    $var wire 64 m st[11] [63:0] $end
    $var wire 64 o st[12] [63:0] $end
    $var wire 64 q st[13] [63:0] $end
    $var wire 64 s st[14] [63:0] $end
    $var wire 64 u st[15] [63:0] $end
    $var wire 64 w st[16] [63:0] $end
    $var wire 64 y st[17] [63:0] $end
    $var wire 64 { st[18] [63:0] $end
    $var wire 64 } st[19] [63:0] $end
    $var wire 64 !! st[20] [63:0] $end
    $var wire 64 #! st[21] [63:0] $end
    $var wire 64 %! st[22] [63:0] $end
    $var wire 64 '! st[23] [63:0] $end
    $var wire 64 )! st[24] [63:0] $end
    $var wire 64 +! stn[0] [63:0] $end
    $var wire 64 -! stn[1] [63:0] $end
    $var wire 64 /! stn[2] [63:0] $end
    $var wire 64 1! stn[3] [63:0] $end
    $var wire 64 3! stn[4] [63:0] $end
    $var wire 64 5! stn[5] [63:0] $end
    $var wire 64 7! stn[6] [63:0] $end
    $var wire 64 9! stn[7] [63:0] $end
    $var wire 64 ;! stn[8] [63:0] $end
    $var wire 64 =! stn[9] [63:0] $end
    $var wire 64 ?! stn[10] [63:0] $end
    $var wire 64 A! stn[11] [63:0] $end
    $var wire 64 C! stn[12] [63:0] $end
    $var wire 64 E! stn[13] [63:0] $end
    $var wire 64 G! stn[14] [63:0] $end
    $var wire 64 I! stn[15] [63:0] $end
    $var wire 64 K! stn[16] [63:0] $end
    $var wire 64 M! stn[17] [63:0] $end
    $var wire 64 O! stn[18] [63:0] $end
    $var wire 64 Q! stn[19] [63:0] $end
    $var wire 64 S! stn[20] [63:0] $end
    $var wire 64 U! stn[21] [63:0] $end
    $var wire 64 W! stn[22] [63:0] $end
    $var wire 64 Y! stn[23] [63:0] $end
    $var wire 64 [! stn[24] [63:0] $end
    $var wire 64 ]! bc[0] [63:0] $end
    $var wire 64 _! bc[1] [63:0] $end
    $var wire 64 a! bc[2] [63:0] $end
    $var wire 64 c! bc[3] [63:0] $end
    $var wire 64 e! bc[4] [63:0] $end
    $var wire 64 g! t [63:0] $end
    $var wire 5 i! round [4:0] $end
    $var wire 5 0" roundlimit [4:0] $end
    $var wire 144 1" rotc [143:0] $end
    $var wire 120 6" piln [119:0] $end
    $var wire 1536 :" rndc [1535:0] $end
    $var wire 1 j! ready_reg $end
   $upscope $end
  $upscope $end
 $upscope $end
$enddefinitions $end


#0
b00000000000000000000000000000101 #
b00000000000000000000000000011001 $
b0000000000000000000000000000000000000000000000000000000000000000 %
b0000000000000000000000000000000000000000000000000000000000000000 '
b0000000000000000000000000000000000000000000000000000000000000000 )
b0000000000000000000000000000000000000000000000000000000000000000 +
b0000000000000000000000000000000000000000000000000000000000000000 -
b0000000000000000000000000000000000000000000000000000000000000000 /
b0000000000000000000000000000000000000000000000000000000000000000 1
b0000000000000000000000000000000000000000000000000000000000000000 3
b0000000000000000000000000000000000000000000000000000000000000000 5
b0000000000000000000000000000000000000000000000000000000000000000 7
b0000000000000000000000000000000000000000000000000000000000000000 9
b0000000000000000000000000000000000000000000000000000000000000000 ;
b0000000000000000000000000000000000000000000000000000000000000000 =
b0000000000000000000000000000000000000000000000000000000000000000 ?
b0000000000000000000000000000000000000000000000000000000000000000 A
b0000000000000000000000000000000000000000000000000000000000000000 C
b0000000000000000000000000000000000000000000000000000000000000000 E
b0000000000000000000000000000000000000000000000000000000000000000 G
b0000000000000000000000000000000000000000000000000000000000000000 I
b0000000000000000000000000000000000000000000000000000000000000000 K
b0000000000000000000000000000000000000000000000000000000000000000 M
b0000000000000000000000000000000000000000000000000000000000000000 O
b0000000000000000000000000000000000000000000000000000000000000000 Q
b0000000000000000000000000000000000000000000000000000000000000000 S
b0000000000000000000000000000000000000000000000000000000000000000 U
b0000000000000000000000000000000000000000000000000000000000000000 W
b0000000000000000000000000000000000000000000000000000000000000000 Y
b0000000000000000000000000000000000000000000000000000000000000000 [
b0000000000000000000000000000000000000000000000000000000000000000 ]
b0000000000000000000000000000000000000000000000000000000000000000 _
b0000000000000000000000000000000000000000000000000000000000000000 a
b0000000000000000000000000000000000000000000000000000000000000000 c
b0000000000000000000000000000000000000000000000000000000000000000 e
b0000000000000000000000000000000000000000000000000000000000000000 g
b0000000000000000000000000000000000000000000000000000000000000000 i
b0000000000000000000000000000000000000000000000000000000000000000 k
b0000000000000000000000000000000000000000000000000000000000000000 m
b0000000000000000000000000000000000000000000000000000000000000000 o
b0000000000000000000000000000000000000000000000000000000000000000 q
b0000000000000000000000000000000000000000000000000000000000000000 s
b0000000000000000000000000000000000000000000000000000000000000000 u
b0000000000000000000000000000000000000000000000000000000000000000 w
b0000000000000000000000000000000000000000000000000000000000000000 y
b0000000000000000000000000000000000000000000000000000000000000000 {
b0000000000000000000000000000000000000000000000000000000000000000 }
b0000000000000000000000000000000000000000000000000000000000000000 !!
b0000000000000000000000000000000000000000000000000000000000000000 #!
b0000000000000000000000000000000000000000000000000000000000000000 %!
b0000000000000000000000000000000000000000000000000000000000000000 '!
b0000000000000000000000000000000000000000000000000000000000000000 )!
b0000000000000000000000000000000000000000000000000000000000000001 +!
b0000000000000000000000000000000000000000000000000000000000000000 -!
b0000000000000000000000000000000000000000000000000000000000000000 /!
b0000000000000000000000000000000000000000000000000000000000000000 1!
b0000000000000000000000000000000000000000000000000000000000000000 3!
b0000000000000000000000000000000000000000000000000000000000000000 5!
b0000000000000000000000000000000000000000000000000000000000000000 7!
b0000000000000000000000000000000000000000000000000000000000000000 9!
b0000000000000000000000000000000000000000000000000000000000000000 ;!
b0000000000000000000000000000000000000000000000000000000000000000 =!
b0000000000000000000000000000000000000000000000000000000000000000 ?!
b0000000000000000000000000000000000000000000000000000000000000000 A!
b0000000000000000000000000000000000000000000000000000000000000000 C!
b0000000000000000000000000000000000000000000000000000000000000000 E!
b0000000000000000000000000000000000000000000000000000000000000000 G!
b0000000000000000000000000000000000000000000000000000000000000000 I!
b0000000000000000000000000000000000000000000000000000000000000000 K!
b0000000000000000000000000000000000000000000000000000000000000000 M!
b0000000000000000000000000000000000000000000000000000000000000000 O!
b0000000000000000000000000000000000000000000000000000000000000000 Q!
b0000000000000000000000000000000000000000000000000000000000000000 S!
b0000000000000000000000000000000000000000000000000000000000000000 U!
b0000000000000000000000000000000000000000000000000000000000000000 W!
b0000000000000000000000000000000000000000000000000000000000000000 Y!
b0000000000000000000000000000000000000000000000000000000000000000 [!
b0000000000000000000000000000000000000000000000000000000000000000 ]!
b0000000000000000000000000000000000000000000000000000000000000000 _!
b0000000000000000000000000000000000000000000000000000000000000000 a!
b0000000000000000000000000000000000000000000000000000000000000000 c!
b0000000000000000000000000000000000000000000000000000000000000000 e!
b0000000000000000000000000000000000000000000000000000000000000000 g!
b00000 i!
1j!
b000 k!
0l!
b000000 m!
b00000000 n!
0o!
0p!
0q!
0r!
0s!
b00000000000000000000000000000000 t!
b00000000 u!
0v!
b0000000 w!
1x!
1y!
b00000000000000000000000000000000 z!
b00000000 {!
b000000 |!
0}!
0~!
b00000000000000000000000000000000 !"
b00000000000000000000000000000000 ""
1#"
0$"
b000 %"
b101011 &"
b000 '"
0("
0)"
b00000000000000000000000000000000 *"
b000 +"
b001 ,"
b010 -"
b011 ."
0/"
b10111 0"
b000001000011000110001010001111010101011100100100101101110111000010001110011011101001111000001000011001101011111110010010100111111101010100101100 1"
b010100011101011100011001000011001011000001000101011100000100011111011110011011010110000010101000111010110010010011000001 6"
b000000000000000000000000000000000000000000000000000000000000000100000000000000000000000000000000000000000000000010000000100000101000000000000000000000000000000000000000000000001000000010001010100000000000000000000000000000001000000000000000100000000000000000000000000000000000000000000000000000000000000010000000100010110000000000000000000000000000000010000000000000000000000000000001100000000000000000000000000000001000000000000000100000001000000110000000000000000000000000000000000000000000000010000000000010010000000000000000000000000000000000000000000000000000000010001010000000000000000000000000000000000000000000000000000000001000100000000000000000000000000000000000100000000000000010000000000010010000000000000000000000000000000010000000000000000000000000001010000000000000000000000000000000001000000000000000100000001000101110000000000000000000000000000000000000000000000000000000100010111000000000000000000000000000000000000000000000001000000010001001100000000000000000000000000000000000000000000000100000000000001110000000000000000000000000000000000000000000000010000000000000101000000000000000000000000000000000000000000000000000000010000000000000000000000000000000000000000000000000000000100000000000101010000000000000000000000000000000100000000000000000000000000010101000000000000000000000000000000010000000000000001000000010000001100000000000000000000000000000000000000000000000100000001000000000000000000000000000000000000000100000000000000000000000000000011000000000000000000000000000000010000000000000001000000000001000 :"
#1
0x!
0y!
#2
b00000000000000000000000000011001 #
b0000000000000000000000000000000000000000000000000000000000000000 +!
b11000 i!
1l!
1x!
1y!
b00000001 {!
b000100 |!
#3
0x!
b00110100001100110011001000110001 z!
1}!
b001 %"
#4
b001 k!
1x!
b010 %"
#5
0x!
#6
b010 k!
0l!
1o!
1x!
b001 '"
#7
0x!
#8
1l!
b000001 m!
1p!
1r!
b00110100001100110011001000110001 t!
1x!
b010 '"
#9
0x!
#10
b0000000000000000000000000000000000110100001100110011001000110001 %
b000010 m!
1q!
b00000000000000000000000000011111 t!
b00000100 u!
b0000001 w!
1x!
b00000000000000000000000000000100 ""
#11
0x!
#12
b0000000000000000000000000001111100110100001100110011001000110001 %
b000011 m!
b00000000000000000000000000000000 t!
b00001000 u!
b0000010 w!
1x!
b00000000000000000000000000001000 ""
#13
0x!
#14
b000100 m!
b00001100 u!
b0000011 w!
1x!
b00000000000000000000000000001100 ""
#15
0x!
#16
b000101 m!
b00010000 u!
b0000100 w!
1x!
b00000000000000000000000000010000 ""
#17
0x!
#18
b000110 m!
b00010100 u!
b0000101 w!
1x!
b00000000000000000000000000010100 ""
#19
0x!
#20
b000111 m!
b00011000 u!
b0000110 w!
1x!
b00000000000000000000000000011000 ""
#21
0x!
#22
b001000 m!
b00011100 u!
b0000111 w!
1x!
b00000000000000000000000000011100 ""
#23
0x!
#24
b001001 m!
b00100000 u!
b0001000 w!
1x!
b00000000000000000000000000100000 ""
#25
0x!
#26
b001010 m!
b00100100 u!
b0001001 w!
1x!
b00000000000000000000000000100100 ""
#27
0x!
#28
b001011 m!
b00101000 u!
b0001010 w!
1x!
b00000000000000000000000000101000 ""
#29
0x!
#30
b001100 m!
b00101100 u!
b0001011 w!
1x!
b00000000000000000000000000101100 ""
#31
0x!
#32
b001101 m!
b00110000 u!
b0001100 w!
1x!
b00000000000000000000000000110000 ""
#33
0x!
#34
b001110 m!
b00110100 u!
b0001101 w!
1x!
b00000000000000000000000000110100 ""
#35
0x!
#36
b001111 m!
b00111000 u!
b0001110 w!
1x!
b00000000000000000000000000111000 ""
#37
0x!
#38
b010000 m!
b00111100 u!
b0001111 w!
1x!
b00000000000000000000000000111100 ""
#39
0x!
#40
b010001 m!
b01000000 u!
b0010000 w!
1x!
b00000000000000000000000001000000 ""
#41
0x!
#42
b010010 m!
b01000100 u!
b0010001 w!
1x!
b00000000000000000000000001000100 ""
#43
0x!
#44
b010011 m!
b01001000 u!
b0010010 w!
1x!
b00000000000000000000000001001000 ""
#45
0x!
#46
b010100 m!
b01001100 u!
b0010011 w!
1x!
b00000000000000000000000001001100 ""
#47
0x!
#48
b010101 m!
b01010000 u!
b0010100 w!
1x!
b00000000000000000000000001010000 ""
#49
0x!
#50
b010110 m!
b01010100 u!
b0010101 w!
1x!
b00000000000000000000000001010100 ""
#51
0x!
#52
b010111 m!
b01011000 u!
b0010110 w!
1x!
b00000000000000000000000001011000 ""
#53
0x!
#54
b011000 m!
b01011100 u!
b0010111 w!
1x!
b00000000000000000000000001011100 ""
#55
0x!
#56
b011001 m!
b01100000 u!
b0011000 w!
1x!
b00000000000000000000000001100000 ""
#57
0x!
#58
b011010 m!
b01100100 u!
b0011001 w!
1x!
b00000000000000000000000001100100 ""
#59
0x!
#60
b011011 m!
b01101000 u!
b0011010 w!
1x!
b00000000000000000000000001101000 ""
#61
0x!
#62
b011100 m!
b01101100 u!
b0011011 w!
1x!
b00000000000000000000000001101100 ""
#63
0x!
#64
b011101 m!
b01110000 u!
b0011100 w!
1x!
b00000000000000000000000001110000 ""
#65
0x!
#66
b011110 m!
b01110100 u!
b0011101 w!
1x!
b00000000000000000000000001110100 ""
#67
0x!
#68
b011111 m!
b01111000 u!
b0011110 w!
1x!
b00000000000000000000000001111000 ""
#69
0x!
#70
b100000 m!
b01111100 u!
b0011111 w!
1x!
b00000000000000000000000001111100 ""
#71
0x!
#72
b100001 m!
b10000000 u!
b0100000 w!
1x!
b00000000000000000000000010000000 ""
#73
0x!
#74
b100010 m!
b10000100 u!
b0100001 w!
1x!
b00000000000000000000000010000100 ""
#75
0x!
#76
b100011 m!
b10001000 u!
b0100010 w!
1x!
b00000000000000000000000010001000 ""
#77
0x!
#78
b100100 m!
b10001100 u!
b0100011 w!
1x!
b00000000000000000000000010001100 ""
#79
0x!
#80
b100101 m!
b10010000 u!
b0100100 w!
1x!
b00000000000000000000000010010000 ""
#81
0x!
#82
b100110 m!
b10010100 u!
b0100101 w!
1x!
b00000000000000000000000010010100 ""
#83
0x!
#84
b100111 m!
b10011000 u!
b0100110 w!
1x!
b00000000000000000000000010011000 ""
#85
0x!
