sha3.v
//======================================================================
// sha3
// ----
// keccak, SHA-3 winner
// derived from "readable keccak"
// 19-Nov-11  Markku-Juhani O. Saarinen <mjos@iki.fi>
// A baseline Keccak (3rd round) implementation.
// Verilog implementation (c) 2015 by Bernd Paysan
// Ported to Cryptech Alpha platform by Pavel Shatov
//
// Redistribution and use in source and binary forms, with or without
// modification, are permitted provided that the following conditions are
// met:
// - Redistributions of source code must retain the above copyright notice,
//   this list of conditions and the following disclaimer.
//
// - Redistributions in binary form must reproduce the above copyright
//   notice, this list of conditions and the following disclaimer in the
//   documentation and/or other materials provided with the distribution.
//
// - Neither the name of the NORDUnet nor the names of its contributors may
//   be used to endorse or promote products derived from this software
//   without specific prior written permission.
//
// THIS SOFTWARE IS PROVIDED BY THE COPYRIGHT HOLDERS AND CONTRIBUTORS "AS
// IS" AND ANY EXPRESS OR IMPLIED WARRANTIES, INCLUDING, BUT NOT LIMITED
// TO, THE IMPLIED WARRANTIES OF MERCHANTABILITY AND FITNESS FOR A
// PARTICULAR PURPOSE ARE DISCLAIMED. IN NO EVENT SHALL THE COPYRIGHT
// HOLDER OR CONTRIBUTORS BE LIABLE FOR ANY DIRECT, INDIRECT, INCIDENTAL,
// SPECIAL, EXEMPLARY, OR CONSEQUENTIAL DAMAGES (INCLUDING, BUT NOT LIMITED
// TO, PROCUREMENT OF SUBSTITUTE GOODS OR SERVICES; LOSS OF USE, DATA, OR
// PROFITS; OR BUSINESS INTERRUPTION) HOWEVER CAUSED AND ON ANY THEORY OF
// LIABILITY, WHETHER IN CONTRACT, STRICT LIABILITY, OR TORT (INCLUDING
// NEGLIGENCE OR OTHERWISE) ARISING IN ANY WAY OUT OF THE USE OF THIS
// SOFTWARE, EVEN IF ADVISED OF THE POSSIBILITY OF SUCH DAMAGE.
//
//======================================================================

`define rotl64(x, r) ((({x, x}<<r)>>64)& 64'hffffffffffffffff)
`define rotci(i) ((rotc>>((23-i)*6)) & 6'h3f)
`define pilni(i) ((piln>>((23-i)*5)) & 5'h1f)
`define rndci(i) ((rndc>>((23-i)*64)) & 64'hffffffffffffffff)

`define SHA3_NUM_ROUNDS         5'd24
/* verilator lint_off WIDTH */
module sha3(    input wire          clk,
                input wire 	     nreset,
                input wire 	     w,
                input wire [ 8:2]    addr,
                input wire [32-1:0]  din,
                output wire [32-1:0] dout,
                input wire 	     init,
                input wire 	     next,
                output wire 	     ready);


   /*
    * The SHA-3 algorithm really wants everything to be little-endian,
    * which is at odds with everything else in our system (including the
    * register interface to sha3_wrapper). Rather than trying to rewrite
    * Bernd's beautiful code, I'll isolate it in its own little-endian
    * universe by byte-swapping all reads and writes.
    */

   reg [31:0]                       dout_swap;
   assign dout = {dout_swap[7:0], dout_swap[15:8], dout_swap[23:16], dout_swap[31:24]};

   wire [31:0]                      din_swap;
   assign din_swap = {din[7:0], din[15:8], din[23:16], din[31:24]};


   integer                          i, j;

   reg [64-1:0]                     blk[0:24],  // input block
                                    st [0:24],  // current state
                                    stn[0:24],  // new state
                                    bc [0: 4],  // intermediate values
                                    t;          // temporary variable

   reg [   4:0]                     round;      // counter value


   localparam   [ 4: 0] roundlimit = `SHA3_NUM_ROUNDS - 'b1;


   localparam   [24*6-1:0]      rotc =
                                      { 6'h01, 6'h03, 6'h06, 6'h0A, 6'h0F, 6'h15,
                                        6'h1C, 6'h24, 6'h2D, 6'h37, 6'h02, 6'h0E,
                                        6'h1B, 6'h29, 6'h38, 6'h08, 6'h19, 6'h2B,
                                        6'h3E, 6'h12, 6'h27, 6'h3D, 6'h14, 6'h2C};

   localparam   [24*5-1:0]      piln =
                                      { 5'h0A, 5'h07, 5'h0B, 5'h11, 5'h12, 5'h03,
                                        5'h05, 5'h10, 5'h08, 5'h15, 5'h18, 5'h04,
                                        5'h0F, 5'h17, 5'h13, 5'h0D, 5'h0C, 5'h02,
                                        5'h14, 5'h0E, 5'h16, 5'h09, 5'h06, 5'h01};

   localparam   [24*64-1:0]     rndc =
                                      { 64'h0000000000000001, 64'h0000000000008082,
                                        64'h800000000000808a, 64'h8000000080008000,
                                        64'h000000000000808b, 64'h0000000080000001,
                                        64'h8000000080008081, 64'h8000000000008009,
                                        64'h000000000000008a, 64'h0000000000000088,
                                        64'h0000000080008009, 64'h000000008000000a,
                                        64'h000000008000808b, 64'h800000000000008b,
                                        64'h8000000000008089, 64'h8000000000008003,
                                        64'h8000000000008002, 64'h8000000000000080,
                                        64'h000000000000800a, 64'h800000008000000a,
                                        64'h8000000080008081, 64'h8000000000008080,
                                        64'h0000000080000001, 64'h8000000080008008};

   /* input block buffer is mapped to the lower half of the
    address space, sponge state is mapped to the upper one */

   /* the lowest address bit determines what part of 64-bit word to return */

   always @*
     //
     dout_swap = addr[8] ?
                 (~addr[2] ? st [addr[7:3]][31:0] : st [addr[7:3]][63:32]) :
                 (~addr[2] ? blk[addr[7:3]][31:0] : blk[addr[7:3]][63:32]) ;


   always @* begin

      // theta1
      for (i=0; i<25; i=i+1)
        stn[i] = st[i];

      for (i=0; i<5; i=i+1)
        bc[i] = stn[i] ^ stn[i+5] ^ stn[i+10] ^ stn[i+15] ^ stn[i+20];

      // theta2
      for (i=0; i<5; i=i+1) begin

         t = bc[(i+4)%5] ^ `rotl64(bc[(i+1)%5], 1);

         for(j=i; j<25; j=j+5)
           stn[j] = t ^ stn[j];
      end

      // rophi
      t = stn[1];
      for(i=0; i<24; i=i+1) begin
         j = `pilni(i);
         { stn[j], t } = { `rotl64(t, `rotci(i)), stn[j] };
      end

      // chi
      for (j=0; j<25; j=j+5) begin

         for (i=0; i<5; i=i+1)
           bc[i] = stn[j + i];

         for (i=0; i<5; i=i+1)
           stn[j+i] = stn[j+i] ^ (~bc[(i+1)%5] & bc[(i+2)%5]);
      end

      // iota
      stn[0] = stn[0] ^ `rndci(round);
   end


   /* ready flag logic */

   reg  ready_reg = 'b1;
   assign ready = ready_reg;

   always @(posedge clk or negedge nreset)
     //
     if (!nreset)       ready_reg <= 'b1;
     else begin
        if (ready)      ready_reg <= !(init || next);
        else            ready_reg <= !(round < roundlimit);
     end

   /* state update logic */
   always @(posedge clk or negedge nreset)
     //
     if (!nreset) begin

        for (i=0; i<25; i=i+1) begin
           st[i]        <= 64'hX;       // wipe state
           blk[i]       <= 64'h0;       // wipe block
        end

        round           <= `SHA3_NUM_ROUNDS;

     end else begin

        if (!ready) begin

           for (i=0; i<25; i=i+1)
             st[i] <= stn[i];

           round <= round + 'd1;

        end else if (init || next) begin

           for (i=0; i<25; i=i+1)
             st[i] <= init ? blk[i] : st[i] ^ blk[i];   // init has priority over next

           round <= 'd0;

        end

        if (w)
          //
          case (addr[2])
            1: blk[addr[7:3]][63:32] <= din_swap;
            0: blk[addr[7:3]][31: 0] <= din_swap;
          endcase

     end


endmodule // sha3
/* verilator lint_on WIDTH */
//======================================================================

SHAKE_wrapper.sv
module SHAKE_wrapper(
        input logic         clk,
        input logic         rst_n,
        input logic [31:0]  seed_buffer,
        input logic [7:0]   absorb_num,        //一共需要吸收的块的数量
        input logic [7:0]   last_block_bytes,  //最后一块数据的字节数
        input logic         init,
        input logic         mode,              // 0 for SHAKE128, 1 for SHAKE256

        output logic [31:0] dout,
        output logic [31:0] addr_seed,
        output logic        ready,
        output logic        valid
    );
    // Internal signals
    logic        nreset;
    logic        wr_keccak;
    logic [6:0]  addr_keccak;
    logic [31:0] din_keccak;
    logic [31:0] dout_keccak;
    logic        init_keccak;
    logic        next_keccak;
    logic        ready_keccak;

    assign nreset = rst_n;
    // State machine states
    logic [2:0] state, next_state,last_state;
    localparam IDLE        = 3'd0,
               ABSORB      = 3'd1,
               SQUEEZE     = 3'd2,
               DONE        = 3'd3;
    // State machine
    always_ff @(posedge clk or negedge rst_n) begin
        if (!rst_n) begin
            state <= IDLE;
            last_state <= IDLE;
        end else begin
            state <= next_state;
            last_state <= state;
        end
            
    end
    // Next state logic
    always_comb begin
        case(state)
            IDLE: begin
                if (init)
                    next_state = ABSORB;
                else
                    next_state = IDLE;
            end
            ABSORB: begin
                if (absorb_done)
                    next_state = SQUEEZE;
                else
                    next_state = ABSORB;
            end
            SQUEEZE: begin
                if (last_block_bytes == 0)
                    next_state = DONE;
                else
                    next_state = SQUEEZE;
            end
            DONE: begin
                next_state = IDLE;
            end
            default: next_state = IDLE;
        endcase
    end
    // Control signals and data path
    logic absorb_done;
    logic [7:0] cnt_total,cnt_once;
    logic [7:0] ABSORB_CNT_ONCE = mode ? 8'd34 : 8'd42;

    always_ff@(posedge clk or negedge rst_n) begin:counter
        if(!rst_n)begin
            cnt_once<=8'b0;
            cnt_total<=8'b0;
        end else begin
            if(next_state==ABSORB && state!=ABSORB)begin
                cnt_once<=8'b0;
                cnt_total<=8'b0;
            end else begin
                if(ready_keccak && state == ABSORB) begin
                    if(cnt_once < ABSORB_CNT_ONCE && !init_keccak) begin
                        cnt_once<=cnt_once+8'b1;
                        wr_keccak<=1'b1;
                    end else begin
                        if(cnt_total<absorb_num)begin
                            cnt_total<=cnt_total+8'b1;
                            cnt_once<=8'b0;
                            wr_keccak<=1'b0;
                        end else begin
                            absorb_done<=1'b1;
                            wr_keccak<=1'b0;
                        end
                        end
                end
            end
        end
    end

    always_ff@(posedge clk or negedge rst_n) begin
        if(!rst_n)begin
            init_keccak<=1'b0;
            next_keccak<=1'b0;
        end else begin
            if(cnt_once==ABSORB_CNT_ONCE && cnt_total != absorb_num)begin
                init_keccak<=1'b1;
            end else begin
                init_keccak<=1'b0;
            end
        end
    end

    sha3 u_sha3(
             .clk    	(clk     ),
             .nreset 	(nreset  ),
             .w      	(wr_keccak ),
             .addr   	(addr_keccak    ),
             .din    	(din_keccak     ),
             .dout   	(dout_keccak    ),
             .init   	(init_keccak    ),
             .next   	(next_keccak    ),
             .ready  	(ready_keccak   )
         );

endmodule

waveform.vcd
$version Generated by VerilatedVcd $end
$timescale 1ps $end
 $scope module TOP $end
  $var wire 1 t! clk $end
  $var wire 1 u! rst_n $end
  $var wire 32 v! seed_buffer [31:0] $end
  $var wire 8 w! absorb_num [7:0] $end
  $var wire 8 x! last_block_bytes [7:0] $end
  $var wire 1 y! init $end
  $var wire 1 z! mode $end
  $var wire 32 {! dout [31:0] $end
  $var wire 32 |! addr_seed [31:0] $end
  $var wire 1 }! ready $end
  $var wire 1 ~! valid $end
  $scope module SHAKE_wrapper $end
   $var wire 1 t! clk $end
   $var wire 1 u! rst_n $end
   $var wire 32 v! seed_buffer [31:0] $end
   $var wire 8 w! absorb_num [7:0] $end
   $var wire 8 x! last_block_bytes [7:0] $end
   $var wire 1 y! init $end
   $var wire 1 z! mode $end
   $var wire 32 {! dout [31:0] $end
   $var wire 32 |! addr_seed [31:0] $end
   $var wire 1 }! ready $end
   $var wire 1 ~! valid $end
   $var wire 1 u! nreset $end
   $var wire 1 # wr_keccak $end
   $var wire 7 #" addr_keccak [6:0] $end
   $var wire 32 $" din_keccak [31:0] $end
   $var wire 32 $ dout_keccak [31:0] $end
   $var wire 1 % init_keccak $end
   $var wire 1 & next_keccak $end
   $var wire 1 ' ready_keccak $end
   $var wire 3 ( state [2:0] $end
   $var wire 3 !" next_state [2:0] $end
   $var wire 3 ) last_state [2:0] $end
   $var wire 3 %" IDLE [2:0] $end
   $var wire 3 &" ABSORB [2:0] $end
   $var wire 3 '" SQUEEZE [2:0] $end
   $var wire 3 (" DONE [2:0] $end
   $var wire 1 * absorb_done $end
   $var wire 8 + cnt_total [7:0] $end
   $var wire 8 , cnt_once [7:0] $end
   $var wire 8 "" ABSORB_CNT_ONCE [7:0] $end
   $scope module u_sha3 $end
    $var wire 1 t! clk $end
    $var wire 1 u! nreset $end
    $var wire 1 # w $end
    $var wire 7 #" addr [8:2] $end
    $var wire 32 $" din [31:0] $end
    $var wire 32 $ dout [31:0] $end
    $var wire 1 % init $end
    $var wire 1 & next $end
    $var wire 1 ' ready $end
    $var wire 32 $ dout_swap [31:0] $end
    $var wire 32 $" din_swap [31:0] $end
    $var wire 32 - i [31:0] $end
    $var wire 32 . j [31:0] $end
    $var wire 64 / blk[0] [63:0] $end
    $var wire 64 1 blk[1] [63:0] $end
    $var wire 64 3 blk[2] [63:0] $end
    $var wire 64 5 blk[3] [63:0] $end
    $var wire 64 7 blk[4] [63:0] $end
    $var wire 64 9 blk[5] [63:0] $end
    $var wire 64 ; blk[6] [63:0] $end
    $var wire 64 = blk[7] [63:0] $end
    $var wire 64 ? blk[8] [63:0] $end
    $var wire 64 A blk[9] [63:0] $end
    $var wire 64 C blk[10] [63:0] $end
    $var wire 64 E blk[11] [63:0] $end
    $var wire 64 G blk[12] [63:0] $end
    $var wire 64 I blk[13] [63:0] $end
    $var wire 64 K blk[14] [63:0] $end
    $var wire 64 M blk[15] [63:0] $end
    $var wire 64 O blk[16] [63:0] $end
    $var wire 64 Q blk[17] [63:0] $end
    $var wire 64 S blk[18] [63:0] $end
    $var wire 64 U blk[19] [63:0] $end
    $var wire 64 W blk[20] [63:0] $end
    $var wire 64 Y blk[21] [63:0] $end
    $var wire 64 [ blk[22] [63:0] $end
    $var wire 64 ] blk[23] [63:0] $end
    $var wire 64 _ blk[24] [63:0] $end
    $var wire 64 a st[0] [63:0] $end
    $var wire 64 c st[1] [63:0] $end
    $var wire 64 e st[2] [63:0] $end
    $var wire 64 g st[3] [63:0] $end
    $var wire 64 i st[4] [63:0] $end
    $var wire 64 k st[5] [63:0] $end
    $var wire 64 m st[6] [63:0] $end
    $var wire 64 o st[7] [63:0] $end
    $var wire 64 q st[8] [63:0] $end
    $var wire 64 s st[9] [63:0] $end
    $var wire 64 u st[10] [63:0] $end
    $var wire 64 w st[11] [63:0] $end
    $var wire 64 y st[12] [63:0] $end
    $var wire 64 { st[13] [63:0] $end
    $var wire 64 } st[14] [63:0] $end
    $var wire 64 !! st[15] [63:0] $end
    $var wire 64 #! st[16] [63:0] $end
    $var wire 64 %! st[17] [63:0] $end
    $var wire 64 '! st[18] [63:0] $end
    $var wire 64 )! st[19] [63:0] $end
    $var wire 64 +! st[20] [63:0] $end
    $var wire 64 -! st[21] [63:0] $end
    $var wire 64 /! st[22] [63:0] $end
    $var wire 64 1! st[23] [63:0] $end
    $var wire 64 3! st[24] [63:0] $end
    $var wire 64 5! stn[0] [63:0] $end
    $var wire 64 7! stn[1] [63:0] $end
    $var wire 64 9! stn[2] [63:0] $end
    $var wire 64 ;! stn[3] [63:0] $end
    $var wire 64 =! stn[4] [63:0] $end
    $var wire 64 ?! stn[5] [63:0] $end
    $var wire 64 A! stn[6] [63:0] $end
    $var wire 64 C! stn[7] [63:0] $end
    $var wire 64 E! stn[8] [63:0] $end
    $var wire 64 G! stn[9] [63:0] $end
    $var wire 64 I! stn[10] [63:0] $end
    $var wire 64 K! stn[11] [63:0] $end
    $var wire 64 M! stn[12] [63:0] $end
    $var wire 64 O! stn[13] [63:0] $end
    $var wire 64 Q! stn[14] [63:0] $end
    $var wire 64 S! stn[15] [63:0] $end
    $var wire 64 U! stn[16] [63:0] $end
    $var wire 64 W! stn[17] [63:0] $end
    $var wire 64 Y! stn[18] [63:0] $end
    $var wire 64 [! stn[19] [63:0] $end
    $var wire 64 ]! stn[20] [63:0] $end
    $var wire 64 _! stn[21] [63:0] $end
    $var wire 64 a! stn[22] [63:0] $end
    $var wire 64 c! stn[23] [63:0] $end
    $var wire 64 e! stn[24] [63:0] $end
    $var wire 64 g! bc[0] [63:0] $end
    $var wire 64 i! bc[1] [63:0] $end
    $var wire 64 k! bc[2] [63:0] $end
    $var wire 64 m! bc[3] [63:0] $end
    $var wire 64 o! bc[4] [63:0] $end
    $var wire 64 q! t [63:0] $end
    $var wire 5 s! round [4:0] $end
    $var wire 5 )" roundlimit [4:0] $end
    $var wire 144 *" rotc [143:0] $end
    $var wire 120 /" piln [119:0] $end
    $var wire 1536 3" rndc [1535:0] $end
    $var wire 1 ' ready_reg $end
   $upscope $end
  $upscope $end
 $upscope $end
$enddefinitions $end


#0
0#
b00000000000000000000000000000000 $
0%
0&
1'
b000 (
b000 )
0*
b00000000 +
b00000000 ,
b00000000000000000000000000000101 -
b00000000000000000000000000011001 .
b0000000000000000000000000000000000000000000000000000000000000000 /
b0000000000000000000000000000000000000000000000000000000000000000 1
b0000000000000000000000000000000000000000000000000000000000000000 3
b0000000000000000000000000000000000000000000000000000000000000000 5
b0000000000000000000000000000000000000000000000000000000000000000 7
b0000000000000000000000000000000000000000000000000000000000000000 9
b0000000000000000000000000000000000000000000000000000000000000000 ;
b0000000000000000000000000000000000000000000000000000000000000000 =
b0000000000000000000000000000000000000000000000000000000000000000 ?
b0000000000000000000000000000000000000000000000000000000000000000 A
b0000000000000000000000000000000000000000000000000000000000000000 C
b0000000000000000000000000000000000000000000000000000000000000000 E
b0000000000000000000000000000000000000000000000000000000000000000 G
b0000000000000000000000000000000000000000000000000000000000000000 I
b0000000000000000000000000000000000000000000000000000000000000000 K
b0000000000000000000000000000000000000000000000000000000000000000 M
b0000000000000000000000000000000000000000000000000000000000000000 O
b0000000000000000000000000000000000000000000000000000000000000000 Q
b0000000000000000000000000000000000000000000000000000000000000000 S
b0000000000000000000000000000000000000000000000000000000000000000 U
b0000000000000000000000000000000000000000000000000000000000000000 W
b0000000000000000000000000000000000000000000000000000000000000000 Y
b0000000000000000000000000000000000000000000000000000000000000000 [
b0000000000000000000000000000000000000000000000000000000000000000 ]
b0000000000000000000000000000000000000000000000000000000000000000 _
b0000000000000000000000000000000000000000000000000000000000000000 a
b0000000000000000000000000000000000000000000000000000000000000000 c
b0000000000000000000000000000000000000000000000000000000000000000 e
b0000000000000000000000000000000000000000000000000000000000000000 g
b0000000000000000000000000000000000000000000000000000000000000000 i
b0000000000000000000000000000000000000000000000000000000000000000 k
b0000000000000000000000000000000000000000000000000000000000000000 m
b0000000000000000000000000000000000000000000000000000000000000000 o
b0000000000000000000000000000000000000000000000000000000000000000 q
b0000000000000000000000000000000000000000000000000000000000000000 s
b0000000000000000000000000000000000000000000000000000000000000000 u
b0000000000000000000000000000000000000000000000000000000000000000 w
b0000000000000000000000000000000000000000000000000000000000000000 y
b0000000000000000000000000000000000000000000000000000000000000000 {
b0000000000000000000000000000000000000000000000000000000000000000 }
b0000000000000000000000000000000000000000000000000000000000000000 !!
b0000000000000000000000000000000000000000000000000000000000000000 #!
b0000000000000000000000000000000000000000000000000000000000000000 %!
b0000000000000000000000000000000000000000000000000000000000000000 '!
b0000000000000000000000000000000000000000000000000000000000000000 )!
b0000000000000000000000000000000000000000000000000000000000000000 +!
b0000000000000000000000000000000000000000000000000000000000000000 -!
b0000000000000000000000000000000000000000000000000000000000000000 /!
b0000000000000000000000000000000000000000000000000000000000000000 1!
b0000000000000000000000000000000000000000000000000000000000000000 3!
b0000000000000000000000000000000000000000000000000000000000000001 5!
b0000000000000000000000000000000000000000000000000000000000000000 7!
b0000000000000000000000000000000000000000000000000000000000000000 9!
b0000000000000000000000000000000000000000000000000000000000000000 ;!
b0000000000000000000000000000000000000000000000000000000000000000 =!
b0000000000000000000000000000000000000000000000000000000000000000 ?!
b0000000000000000000000000000000000000000000000000000000000000000 A!
b0000000000000000000000000000000000000000000000000000000000000000 C!
b0000000000000000000000000000000000000000000000000000000000000000 E!
b0000000000000000000000000000000000000000000000000000000000000000 G!
b0000000000000000000000000000000000000000000000000000000000000000 I!
b0000000000000000000000000000000000000000000000000000000000000000 K!
b0000000000000000000000000000000000000000000000000000000000000000 M!
b0000000000000000000000000000000000000000000000000000000000000000 O!
b0000000000000000000000000000000000000000000000000000000000000000 Q!
b0000000000000000000000000000000000000000000000000000000000000000 S!
b0000000000000000000000000000000000000000000000000000000000000000 U!
b0000000000000000000000000000000000000000000000000000000000000000 W!
b0000000000000000000000000000000000000000000000000000000000000000 Y!
b0000000000000000000000000000000000000000000000000000000000000000 [!
b0000000000000000000000000000000000000000000000000000000000000000 ]!
b0000000000000000000000000000000000000000000000000000000000000000 _!
b0000000000000000000000000000000000000000000000000000000000000000 a!
b0000000000000000000000000000000000000000000000000000000000000000 c!
b0000000000000000000000000000000000000000000000000000000000000000 e!
b0000000000000000000000000000000000000000000000000000000000000000 g!
b0000000000000000000000000000000000000000000000000000000000000000 i!
b0000000000000000000000000000000000000000000000000000000000000000 k!
b0000000000000000000000000000000000000000000000000000000000000000 m!
b0000000000000000000000000000000000000000000000000000000000000000 o!
b0000000000000000000000000000000000000000000000000000000000000000 q!
b00000 s!
1t!
1u!
b00000000000000000000000000000000 v!
b00000000 w!
b00000000 x!
0y!
0z!
b00000000000000000000000000000000 {!
b00000000000000000000000000000000 |!
0}!
0~!
b000 !"
b00101010 ""
b0000000 #"
b00000000000000000000000000000000 $"
b000 %"
b001 &"
b010 '"
b011 ("
b10111 )"
b000001000011000110001010001111010101011100100100101101110111000010001110011011101001111000001000011001101011111110010010100111111101010100101100 *"
b010100011101011100011001000011001011000001000101011100000100011111011110011011010110000010101000111010110010010011000001 /"
b000000000000000000000000000000000000000000000000000000000000000100000000000000000000000000000000000000000000000010000000100000101000000000000000000000000000000000000000000000001000000010001010100000000000000000000000000000001000000000000000100000000000000000000000000000000000000000000000000000000000000010000000100010110000000000000000000000000000000010000000000000000000000000000001100000000000000000000000000000001000000000000000100000001000000110000000000000000000000000000000000000000000000010000000000010010000000000000000000000000000000000000000000000000000000010001010000000000000000000000000000000000000000000000000000000001000100000000000000000000000000000000000100000000000000010000000000010010000000000000000000000000000000010000000000000000000000000001010000000000000000000000000000000001000000000000000100000001000101110000000000000000000000000000000000000000000000000000000100010111000000000000000000000000000000000000000000000001000000010001001100000000000000000000000000000000000000000000000100000000000001110000000000000000000000000000000000000000000000010000000000000101000000000000000000000000000000000000000000000000000000010000000000000000000000000000000000000000000000000000000100000000000101010000000000000000000000000000000100000000000000000000000000010101000000000000000000000000000000010000000000000001000000010000001100000000000000000000000000000000000000000000000100000001000000000000000000000000000000000000000100000000000000000000000000000011000000000000000000000000000000010000000000000001000000000001000 3"
#1
b00000000000000000000000000011001 -
b0000000000000000000000000000000000000000000000000000000000000000 5!
b11000 s!
0t!
0u!
#2
1t!
1u!
b00000001 w!
b00000100 x!
#3
0t!
b00110100001100110011001000110001 v!
1y!
b001 !"
#4
b001 (
1t!
#5
0t!
#6
1#
b001 )
b00000001 ,
1t!
#7
0t!
#8
b00000010 ,
1t!
#9
0t!
#10
b00000011 ,
1t!
#11
0t!
#12
b00000100 ,
1t!
#13
0t!
#14
b00000101 ,
1t!
#15
0t!
#16
b00000110 ,
1t!
#17
0t!
#18
b00000111 ,
1t!
#19
0t!
#20
b00001000 ,
1t!
#21
0t!
#22
b00001001 ,
1t!
#23
0t!
#24
b00001010 ,
1t!
#25
0t!
#26
b00001011 ,
1t!
#27
0t!
#28
b00001100 ,
1t!
#29
0t!
#30
b00001101 ,
1t!
#31
0t!
#32
b00001110 ,
1t!
#33
0t!
#34
b00001111 ,
1t!
#35
0t!
#36
b00010000 ,
1t!
#37
0t!
#38
b00010001 ,
1t!
#39
0t!
#40
b00010010 ,
1t!
#41
0t!
#42
b00010011 ,
1t!
#43
0t!
#44
b00010100 ,
1t!
#45
0t!
#46
b00010101 ,
1t!
#47
0t!
#48
b00010110 ,
1t!
#49
0t!
#50
b00010111 ,
1t!
#51
0t!
#52
b00011000 ,
1t!
#53
0t!
#54
b00011001 ,
1t!
#55
0t!
#56
b00011010 ,
1t!
#57
0t!
#58
b00011011 ,
1t!
#59
0t!
#60
b00011100 ,
1t!
#61
0t!
#62
b00011101 ,
1t!
#63
0t!
#64
b00011110 ,
1t!
#65
0t!
#66
b00011111 ,
1t!
#67
0t!
#68
b00100000 ,
1t!
#69
0t!
#70
b00100001 ,
1t!
#71
0t!
#72
b00100010 ,
1t!
#73
0t!
#74
b00100011 ,
1t!
#75
0t!
#76
b00100100 ,
1t!
#77
0t!
#78
b00100101 ,
1t!
#79
0t!
#80
b00100110 ,
1t!
#81
0t!
#82
b00100111 ,
1t!
#83
0t!
#84
b00101000 ,
1t!
#85
0t!
#86
b00101001 ,
1t!
#87
0t!
#88
b00101010 ,
1t!
#89
0t!
#90
0#
1%
b00000001 +
b00000000 ,
1t!
#91
0t!
#92
0%
0'
1*
b0000000000000000000000000000000000000000000000000000000000000001 5!
b00000 s!
1t!
b010 !"
#93
0t!
#94
b010 (
b0000000000000000000000000000000000000000000000000000000000000001 a
b0000000000000000000000000000000000000000000000001000000010000011 5!
b0000000000000000000100000000000000000000000000000000000000000000 7!
b0000000000000000000000000000000000000000000000001000000000000000 9!
b0000000000000000000000000000000000000000000000000000000000000001 ;!
b0000000000000000000100000000000000000000000000001000000000000000 =!
b0000000000000000001000000000000000000000001000000000000000000000 A!
b0000000000000000001000000000000000000000000000000000000000000000 E!
b0000000000000000000000000000000000000000001000000000000000000000 G!
b0000000000000000000000000000000000000000000000000000000000000010 I!
b0000000000000000000000000000000000000000000000000000001000000000 K!
b0000000000000000000000000000000000000000000000000000001000000010 O!
b0000000000000000000000000000000000010000000000000000010000000000 S!
b0000000000000000000000000000000000000000000000000000010000000000 W!
b0000000000000000000000000000000000010000000000000000000000000000 Y!
b0000000000000000000000010000000000000000000000000000000000000000 ]!
b0000000000000000000000010000000000000000000000000000000000000100 a!
b0000000000000000000000000000000000000000000000000000000000000100 e!
b0000000000000000000000010000000000000000000000000000000000000000 k!
b0000000000000000000000000000000000000000000000000000000000000100 o!
b0000000000000000000000000000000000000000000000000000000000000001 q!
b00001 s!
1t!
#95
0t!
#96
b010 )
b0000000000000000000000000000000000000000000000001000000010000011 a
b0000000000000000000100000000000000000000000000000000000000000000 c
b0000000000000000000000000000000000000000000000001000000000000000 e
b0000000000000000000000000000000000000000000000000000000000000001 g
b0000000000000000000100000000000000000000000000001000000000000000 i
b0000000000000000001000000000000000000000001000000000000000000000 m
b0000000000000000001000000000000000000000000000000000000000000000 q
b0000000000000000000000000000000000000000001000000000000000000000 s
b0000000000000000000000000000000000000000000000000000000000000010 u
b0000000000000000000000000000000000000000000000000000001000000000 w
b0000000000000000000000000000000000000000000000000000001000000010 {
b0000000000000000000000000000000000010000000000000000010000000000 !!
b0000000000000000000000000000000000000000000000000000010000000000 %!
b0000000000000000000000000000000000010000000000000000000000000000 '!
b0000000000000000000000010000000000000000000000000000000000000000 +!
b0000000000000000000000010000000000000000000000000000000000000100 /!
b0000000000000000000000000000000000000000000000000000000000000100 3!
b1000000000110000010100000000000000000001111000001000010000001100 5!
b0011100011001010100110000011000010000010001100000000000100000110 7!
b0000100010110000001101000000000001000001110000010100000100000001 9!
b0010000000000010011110000011000010000001101000000000010010000011 ;!
b0001000001001000100011000000000001000000110100010100000100000000 =!
b0000000000000100100110000100000011010011000001000010001000100000 ?!
b0001000110010011001000100001000010110000011100000000001000000010 A!
b0100000000000011100011100010000000000111000000000010000011110000 C!
b0011000110010101001100000100000011010000011000000000000000010000 E!
b0110000000000011000011000011000000100100000101000000000011000010 G!
b0000000000000000101001010000010000110100000000110001100101010000 I!
b0000000000111110000000000011100000001001000010101000000010000000 K!
b1100010000000000100000101000111000001100000100000000000001000011 M!
b0000000000100010001001100011000000100001000010000001100000010010 O!
b1100010000011100000000011000101000011000000100001000000010000001 Q!
b0000000110000100000011000101100000001110001110000010010110010000 S!
b0011111000001000010100000101000000000001000001100000000000000000 U!
b0000010000001100000000000110000100000110001110100110010110000100 W!
b0011100110000000000111000100100000001001000000110000000000010000 Y!
b0000101000001000010000000010000100000000000001110100000110000100 [!
b1000000010000101100111001000000000001000000110010010000110011001 ]!
b1100011100000000000010000000000010000000111000000010000011100010 _!
b0000000010000101100001001000000001000000000101110011001000011100 a!
b0100000100000000000110000000000000001000111010000000000110100001 c!
b0000011000000000000011000000000011000000000001100011001001100110 e!
b1000000000000000000111000000000000001000000010000010000110000001 g!
b0000011000000000000000000000000010000000000000000010000011000010 i!
b0000000010000101100000001000000000000000000100010000000000011000 k!
b1100000100000000000010000000000000000000111000000000000000100000 m!
b0000000000000000000011000000000001000000000001100011001000100100 o!
b0000000000000000000100110000000000010000000000011000110010001001 q!
b00010 s!
1t!
#97
0t!
