sha3.v
//======================================================================
// sha3
// ----
// keccak, SHA-3 winner
// derived from "readable keccak"
// 19-Nov-11  Markku-Juhani O. Saarinen <mjos@iki.fi>
// A baseline Keccak (3rd round) implementation.
// Verilog implementation (c) 2015 by Bernd Paysan
// Ported to Cryptech Alpha platform by Pavel Shatov
//
// Redistribution and use in source and binary forms, with or without
// modification, are permitted provided that the following conditions are
// met:
// - Redistributions of source code must retain the above copyright notice,
//   this list of conditions and the following disclaimer.
//
// - Redistributions in binary form must reproduce the above copyright
//   notice, this list of conditions and the following disclaimer in the
//   documentation and/or other materials provided with the distribution.
//
// - Neither the name of the NORDUnet nor the names of its contributors may
//   be used to endorse or promote products derived from this software
//   without specific prior written permission.
//
// THIS SOFTWARE IS PROVIDED BY THE COPYRIGHT HOLDERS AND CONTRIBUTORS "AS
// IS" AND ANY EXPRESS OR IMPLIED WARRANTIES, INCLUDING, BUT NOT LIMITED
// TO, THE IMPLIED WARRANTIES OF MERCHANTABILITY AND FITNESS FOR A
// PARTICULAR PURPOSE ARE DISCLAIMED. IN NO EVENT SHALL THE COPYRIGHT
// HOLDER OR CONTRIBUTORS BE LIABLE FOR ANY DIRECT, INDIRECT, INCIDENTAL,
// SPECIAL, EXEMPLARY, OR CONSEQUENTIAL DAMAGES (INCLUDING, BUT NOT LIMITED
// TO, PROCUREMENT OF SUBSTITUTE GOODS OR SERVICES; LOSS OF USE, DATA, OR
// PROFITS; OR BUSINESS INTERRUPTION) HOWEVER CAUSED AND ON ANY THEORY OF
// LIABILITY, WHETHER IN CONTRACT, STRICT LIABILITY, OR TORT (INCLUDING
// NEGLIGENCE OR OTHERWISE) ARISING IN ANY WAY OUT OF THE USE OF THIS
// SOFTWARE, EVEN IF ADVISED OF THE POSSIBILITY OF SUCH DAMAGE.
//
//======================================================================

`define rotl64(x, r) ((({x, x}<<r)>>64)& 64'hffffffffffffffff)
`define rotci(i) ((rotc>>((23-i)*6)) & 6'h3f)
`define pilni(i) ((piln>>((23-i)*5)) & 5'h1f)
`define rndci(i) ((rndc>>((23-i)*64)) & 64'hffffffffffffffff)

`define SHA3_NUM_ROUNDS         5'd24
/* verilator lint_off WIDTH */
module sha3(    input wire          clk,
                input wire 	     nreset,
                input wire 	     w,
                input wire [ 8:2]    addr,
                input wire [32-1:0]  din,
                output wire [32-1:0] dout,
                input wire 	     init,
                input wire 	     next,
                input wire 	     squeeze,
                output wire 	     ready);


   /*
    * The SHA-3 algorithm really wants everything to be little-endian,
    * which is at odds with everything else in our system (including the
    * register interface to sha3_wrapper). Rather than trying to rewrite
    * Bernd's beautiful code, I'll isolate it in its own little-endian
    * universe by byte-swapping all reads and writes.
    */

   reg [31:0]                       dout_swap;
   //assign dout = {dout_swap[7:0], dout_swap[15:8], dout_swap[23:16], dout_swap[31:24]};
   assign dout = dout_swap;

   wire [31:0]                      din_swap;
   //assign din_swap = {din[7:0], din[15:8], din[23:16], din[31:24]};
    assign din_swap = din;

   integer                          i, j;

   reg [64-1:0]                     blk[0:24],  // input block
                                    st [0:24],  // current state
                                    stn[0:24],  // new state
                                    bc [0: 4],  // intermediate values
                                    t;          // temporary variable

   reg [   4:0]                     round;      // counter value


   localparam   [ 4: 0] roundlimit = `SHA3_NUM_ROUNDS - 'b1;


   localparam   [24*6-1:0]      rotc =
                                      { 6'h01, 6'h03, 6'h06, 6'h0A, 6'h0F, 6'h15,
                                        6'h1C, 6'h24, 6'h2D, 6'h37, 6'h02, 6'h0E,
                                        6'h1B, 6'h29, 6'h38, 6'h08, 6'h19, 6'h2B,
                                        6'h3E, 6'h12, 6'h27, 6'h3D, 6'h14, 6'h2C};

   localparam   [24*5-1:0]      piln =
                                      { 5'h0A, 5'h07, 5'h0B, 5'h11, 5'h12, 5'h03,
                                        5'h05, 5'h10, 5'h08, 5'h15, 5'h18, 5'h04,
                                        5'h0F, 5'h17, 5'h13, 5'h0D, 5'h0C, 5'h02,
                                        5'h14, 5'h0E, 5'h16, 5'h09, 5'h06, 5'h01};

   localparam   [24*64-1:0]     rndc =
                                      { 64'h0000000000000001, 64'h0000000000008082,
                                        64'h800000000000808a, 64'h8000000080008000,
                                        64'h000000000000808b, 64'h0000000080000001,
                                        64'h8000000080008081, 64'h8000000000008009,
                                        64'h000000000000008a, 64'h0000000000000088,
                                        64'h0000000080008009, 64'h000000008000000a,
                                        64'h000000008000808b, 64'h800000000000008b,
                                        64'h8000000000008089, 64'h8000000000008003,
                                        64'h8000000000008002, 64'h8000000000000080,
                                        64'h000000000000800a, 64'h800000008000000a,
                                        64'h8000000080008081, 64'h8000000000008080,
                                        64'h0000000080000001, 64'h8000000080008008};

   /* input block buffer is mapped to the lower half of the
    address space, sponge state is mapped to the upper one */

   /* the lowest address bit determines what part of 64-bit word to return */

   always @*
     //
     dout_swap = addr[8] ?
                 (~addr[2] ? st [addr[7:3]][31:0] : st [addr[7:3]][63:32]) :
                 (~addr[2] ? blk[addr[7:3]][31:0] : blk[addr[7:3]][63:32]) ;


   always @* begin

      // theta1
      for (i=0; i<25; i=i+1)
        stn[i] = st[i];

      for (i=0; i<5; i=i+1)
        bc[i] = stn[i] ^ stn[i+5] ^ stn[i+10] ^ stn[i+15] ^ stn[i+20];

      // theta2
      for (i=0; i<5; i=i+1) begin

         t = bc[(i+4)%5] ^ `rotl64(bc[(i+1)%5], 1);

         for(j=i; j<25; j=j+5)
           stn[j] = t ^ stn[j];
      end

      // rophi
      t = stn[1];
      for(i=0; i<24; i=i+1) begin
         j = `pilni(i);
         { stn[j], t } = { `rotl64(t, `rotci(i)), stn[j] };
      end

      // chi
      for (j=0; j<25; j=j+5) begin

         for (i=0; i<5; i=i+1)
           bc[i] = stn[j + i];

         for (i=0; i<5; i=i+1)
           stn[j+i] = stn[j+i] ^ (~bc[(i+1)%5] & bc[(i+2)%5]);
      end

      // iota
      stn[0] = stn[0] ^ `rndci(round);
   end


   /* ready flag logic */

   reg  ready_reg = 'b1;
   assign ready = ready_reg;

   always @(posedge clk or negedge nreset)
     //
     if (!nreset)       ready_reg <= 'b1;
     else begin
        if (ready)      ready_reg <= !(init || next || squeeze);
        else            ready_reg <= !(round < roundlimit);
     end

   /* state update logic */
   always @(posedge clk or negedge nreset)
     //
     if (!nreset) begin

        for (i=0; i<25; i=i+1) begin
           st[i]        <= 64'hX;       // wipe state
           blk[i]       <= 64'h0;       // wipe block
        end

        round           <= `SHA3_NUM_ROUNDS;

     end else begin

        if (!ready) begin

           for (i=0; i<25; i=i+1)
             st[i] <= stn[i];

           round <= round + 'd1;

        end else if (init || next || squeeze) begin

           for (i=0; i<25; i=i+1)
             st[i] <= init ? blk[i] : (squeeze)? st[i] :(st[i] ^ blk[i]);   // init has priority over next

           round <= 'd0;

        end

        if (w)
          //
          case (addr[2])
            1: blk[addr[7:3]][63:32] <= din_swap;
            0: blk[addr[7:3]][31: 0] <= din_swap;
          endcase

     end


endmodule // sha3
/* verilator lint_on WIDTH */
//======================================================================

SHAKE_wrapper.sv
module SHAKE_wrapper(
        input logic         clk,
        input logic         rst_n,
        input logic [31:0]  seed_buffer,
        input logic [7:0]   absorb_num,        //一共需要吸收的块的数量
        input logic [7:0]   last_block_bytes,  //最后一块数据的字节数
        input logic         init,
        input logic         mode,              // 0 for SHAKE128, 1 for SHAKE256

        output logic [31:0] dout,
        output logic [31:0] addr_perip,
        output logic        ready,
        output logic        valid,

        input logic [9:0]  squeeze_num         //一共需要挤出的块的数量   
    );
    // Internal signals
    logic        nreset;
    logic        wr_keccak;
    logic [6:0]  addr_keccak;
    logic [31:0] din_keccak;
    logic [31:0] dout_keccak;
    logic        init_keccak;
    logic        next_keccak_absorb,next_keccak_squeeze;
    logic        ready_keccak;

    logic [31:0] addr_seed,addr_storage;
    logic [7:0]  addr_squeeze;
    assign addr_perip = (state==ABSORB)? addr_seed : addr_storage;
    assign nreset = rst_n;
    // State machine states
    logic [2:0] state, next_state,last_state;
    localparam IDLE        = 3'd0,
               ABSORB      = 3'd1,
               SQUEEZE     = 3'd2,
               DONE        = 3'd3;
    // State machine
    always_ff @(posedge clk or negedge rst_n) begin
        if (!rst_n) begin
            state <= IDLE;
            last_state <= IDLE;
        end else begin
            state <= next_state;
            last_state <= state;
        end
            
    end
    // Next state logic
    always_comb begin
        case(state)
            IDLE: begin
                if (init)
                    next_state = ABSORB;
                else
                    next_state = IDLE;
            end
            ABSORB: begin
                if (absorb_done)
                    next_state = SQUEEZE;
                else
                    next_state = ABSORB;
            end
            SQUEEZE: begin
                if (squeeze_done == 1'b1)
                    next_state = IDLE;
                else
                    next_state = SQUEEZE;
            end
            default: next_state = IDLE;
        endcase
    end
    // Control signals and data path
    logic absorb_done;
    logic [7:0] cnt_total,cnt_once;
    logic [7:0] ABSORB_CNT_ONCE = mode ? 8'd34 : 8'd42;

    always_ff@(posedge clk or negedge rst_n) begin:counter
        if(!rst_n)begin
            cnt_once<=8'b0;
            cnt_total<=8'b0;
        end else begin
            if(next_state==ABSORB && state!=ABSORB)begin
                cnt_once<=8'b0;
                cnt_total<=8'b0;
                addr_seed<=32'b0;
            end else begin
                if(ready_keccak && state == ABSORB) begin
                    if(cnt_once < ABSORB_CNT_ONCE && !init_keccak && !next_keccak_absorb) begin
                        cnt_once<=cnt_once+8'b1;
                        addr_seed<=addr_seed+32'd4;//取地址和wr同时拉高，保证同步写入的时序差一个周期
                        wr_keccak<=1'b1;
                    end else begin
                        if(cnt_total<absorb_num)begin
                            if(cnt_once!=8'd0)begin
                                cnt_total<=cnt_total+8'b1;
                                cnt_once<=8'b0;
                                wr_keccak<=1'b0;
                                if(cnt_once < ABSORB_CNT_ONCE)begin
                                    addr_seed<=addr_seed+32'd4;
                                end
                            end
                        end else begin
                            absorb_done<=1'b1;
                            wr_keccak<=1'b0;
                        end
                        end
                end
            end
        end
    end

    always_ff@(posedge clk or negedge rst_n) begin
        if(!rst_n)begin
            init_keccak<=1'b0;
            next_keccak_absorb<=1'b0;
        end else begin
            if(cnt_once==ABSORB_CNT_ONCE && cnt_total == 8'd0)begin
                init_keccak<=1'b1;
            end else begin
                init_keccak<=1'b0;
            end

            if(cnt_once==ABSORB_CNT_ONCE && cnt_total < absorb_num && cnt_total!=8'd0)begin
                next_keccak_absorb<=1'b1;
            end else begin
                next_keccak_absorb<=1'b0;
            end

        end
    end

    logic [31:0] padding_typeA, padding_mask, padding_typeB;
    logic [7:0] temp_cnt = {2'b00,last_block_bytes[7:2]}+8'd1;

    always_comb begin:din_logic
        //padding_type_A
        if(cnt_once < temp_cnt)begin
            padding_typeA = seed_buffer;
        end else if (cnt_once == temp_cnt) begin
            case(last_block_bytes[1:0])
                    2'b00:padding_typeA = 32'h0000001F;
                    2'b11:padding_typeA ={8'h1F,seed_buffer[23:0]};
                    2'b10:padding_typeA ={16'h001F,seed_buffer[15:0]};
                    2'b01:padding_typeA ={24'h00001F,seed_buffer[7:0]};
                    default:padding_typeA = 32'd0;
            endcase
        end else begin
            padding_typeA = 32'd0;
        end
        //padding_mask
        if(cnt_once == ABSORB_CNT_ONCE && last_block_bytes!=8'd0) begin
            padding_mask = 32'h80000000;
        end else begin
            padding_mask = 32'd0;
        end
        //padding_type_B:空白块填充
        if(cnt_once == 8'd1) begin
            padding_typeB = 32'h0000001F;
        end else if(cnt_once == ABSORB_CNT_ONCE) begin
            padding_typeB = 32'h80000000;
        end else begin
            padding_typeB = 32'd0;
        end

        if(cnt_total != absorb_num-1)begin
            din_keccak = seed_buffer;
        end else begin
            if(last_block_bytes!=8'd0)
            begin
                din_keccak = padding_typeA | padding_mask;
            end else begin
                din_keccak = padding_typeB ;
            end
            
        end
    end
    logic [9:0] squeeze_cnt;
    logic squeeze_done;
    always_ff @(posedge clk or negedge rst_n) begin
        if(!rst_n)begin
            addr_storage<=32'b0;
            addr_squeeze<=8'b0;
            squeeze_cnt<=10'b0;
        end begin
            if(absorb_done && state == ABSORB)begin
                addr_storage<=32'b0;
                addr_squeeze<=8'b0;
                squeeze_cnt<=10'b0;
            end else if(squeeze_cnt < squeeze_num && state == SQUEEZE && ready_keccak ) begin
                if(addr_squeeze < ABSORB_CNT_ONCE-1 ) begin
                    if(!next_keccak_squeeze) begin
                         addr_storage<=addr_storage+32'd4;
                         addr_squeeze<=addr_squeeze+8'd1;
                    end
                    next_keccak_squeeze<=1'b0;
                end else begin
                    if(squeeze_cnt == squeeze_num - 1) begin
                        squeeze_done<=1'b1;
                    end else begin
                        addr_storage<=addr_storage;
                        addr_squeeze<=8'b0;
                        next_keccak_squeeze<=1'b1;
                        squeeze_cnt<=squeeze_cnt+10'b1;
                    end
                end
            end 
        end
    end
    assign valid = (state == SQUEEZE && ready_keccak && !next_keccak_squeeze) ? 1'b1 : 1'b0;
    // Instantiate Keccak module
    assign addr_keccak = (state == ABSORB)? addr_keccak_absorb:{1'b1,addr_squeeze[5:0]};
    logic [6:0] addr_keccak_absorb;
    assign addr_keccak_absorb = cnt_once[6:0] - 7'd1;
    assign dout = dout_keccak;
    sha3 u_sha3(
             .clk    	(clk     ),
             .nreset 	(nreset  ),
             .w      	(wr_keccak ),
             .addr   	(addr_keccak    ),
             .din    	(din_keccak     ),
             .dout   	(dout_keccak    ),
             .init   	(init_keccak    ),
             .next   	(next_keccak_absorb      ),
             .squeeze    (next_keccak_squeeze   ),
             .ready  	(ready_keccak   )
         );

endmodule

waveform.vcd
$version Generated by VerilatedVcd $end
$date Thu Nov 13 18:00:18 2025
 $end
$timescale   1ps $end

 $scope module TOP $end
  $var wire  8 &" absorb_num [7:0] $end
  $var wire 32 +" addr_perip [31:0] $end
  $var wire  1 #" clk $end
  $var wire 32 *" dout [31:0] $end
  $var wire  1 (" init $end
  $var wire  8 '" last_block_bytes [7:0] $end
  $var wire  1 )" mode $end
  $var wire  1 ," ready $end
  $var wire  1 $" rst_n $end
  $var wire 32 %" seed_buffer [31:0] $end
  $var wire 10 ." squeeze_num [9:0] $end
  $var wire  1 -" valid $end
  $scope module SHAKE_wrapper $end
   $var wire  3 2" ABSORB [2:0] $end
   $var wire  8 /" ABSORB_CNT_ONCE [7:0] $end
   $var wire  3 4" DONE [2:0] $end
   $var wire  3 1" IDLE [2:0] $end
   $var wire  3 3" SQUEEZE [2:0] $end
   $var wire  1 / absorb_done $end
   $var wire  8 &" absorb_num [7:0] $end
   $var wire  7 $ addr_keccak [6:0] $end
   $var wire  7 4 addr_keccak_absorb [6:0] $end
   $var wire 32 +" addr_perip [31:0] $end
   $var wire 32 * addr_seed [31:0] $end
   $var wire  8 , addr_squeeze [7:0] $end
   $var wire 32 + addr_storage [31:0] $end
   $var wire  1 #" clk $end
   $var wire  8 1 cnt_once [7:0] $end
   $var wire  8 0 cnt_total [7:0] $end
   $var wire 32 |! din_keccak [31:0] $end
   $var wire 32 *" dout [31:0] $end
   $var wire 32 % dout_keccak [31:0] $end
   $var wire  1 (" init $end
   $var wire  1 & init_keccak $end
   $var wire  8 '" last_block_bytes [7:0] $end
   $var wire  3 . last_state [2:0] $end
   $var wire  1 )" mode $end
   $var wire  1 ' next_keccak_absorb $end
   $var wire  1 ( next_keccak_squeeze $end
   $var wire  3 }! next_state [2:0] $end
   $var wire  1 $" nreset $end
   $var wire 32 !" padding_mask [31:0] $end
   $var wire 32 ~! padding_typeA [31:0] $end
   $var wire 32 "" padding_typeB [31:0] $end
   $var wire  1 ," ready $end
   $var wire  1 ) ready_keccak $end
   $var wire  1 $" rst_n $end
   $var wire 32 %" seed_buffer [31:0] $end
   $var wire 10 2 squeeze_cnt [9:0] $end
   $var wire  1 3 squeeze_done $end
   $var wire 10 ." squeeze_num [9:0] $end
   $var wire  3 - state [2:0] $end
   $var wire  8 0" temp_cnt [7:0] $end
   $var wire  1 -" valid $end
   $var wire  1 # wr_keccak $end
   $scope module u_sha3 $end
    $var wire  7 $ addr [8:2] $end
    $var wire 64 o! bc(0) [63:0] $end
    $var wire 64 q! bc(1) [63:0] $end
    $var wire 64 s! bc(2) [63:0] $end
    $var wire 64 u! bc(3) [63:0] $end
    $var wire 64 w! bc(4) [63:0] $end
    $var wire 64 7 blk(0) [63:0] $end
    $var wire 64 9 blk(1) [63:0] $end
    $var wire 64 K blk(10) [63:0] $end
    $var wire 64 M blk(11) [63:0] $end
    $var wire 64 O blk(12) [63:0] $end
    $var wire 64 Q blk(13) [63:0] $end
    $var wire 64 S blk(14) [63:0] $end
    $var wire 64 U blk(15) [63:0] $end
    $var wire 64 W blk(16) [63:0] $end
    $var wire 64 Y blk(17) [63:0] $end
    $var wire 64 [ blk(18) [63:0] $end
    $var wire 64 ] blk(19) [63:0] $end
    $var wire 64 ; blk(2) [63:0] $end
    $var wire 64 _ blk(20) [63:0] $end
    $var wire 64 a blk(21) [63:0] $end
    $var wire 64 c blk(22) [63:0] $end
    $var wire 64 e blk(23) [63:0] $end
    $var wire 64 g blk(24) [63:0] $end
    $var wire 64 = blk(3) [63:0] $end
    $var wire 64 ? blk(4) [63:0] $end
    $var wire 64 A blk(5) [63:0] $end
    $var wire 64 C blk(6) [63:0] $end
    $var wire 64 E blk(7) [63:0] $end
    $var wire 64 G blk(8) [63:0] $end
    $var wire 64 I blk(9) [63:0] $end
    $var wire  1 #" clk $end
    $var wire 32 |! din [31:0] $end
    $var wire 32 |! din_swap [31:0] $end
    $var wire 32 % dout [31:0] $end
    $var wire 32 % dout_swap [31:0] $end
    $var wire 32 5 i [31:0] $end
    $var wire  1 & init $end
    $var wire 32 6 j [31:0] $end
    $var wire  1 ' next $end
    $var wire  1 $" nreset $end
    $var wire 120 ;" piln [119:0] $end
    $var wire  1 ) ready $end
    $var wire  1 ) ready_reg $end
    $var wire 1536 ?" rndc [1535:0] $end
    $var wire 144 6" rotc [143:0] $end
    $var wire  5 {! round [4:0] $end
    $var wire  5 5" roundlimit [4:0] $end
    $var wire  1 ( squeeze $end
    $var wire 64 i st(0) [63:0] $end
    $var wire 64 k st(1) [63:0] $end
    $var wire 64 } st(10) [63:0] $end
    $var wire 64 !! st(11) [63:0] $end
    $var wire 64 #! st(12) [63:0] $end
    $var wire 64 %! st(13) [63:0] $end
    $var wire 64 '! st(14) [63:0] $end
    $var wire 64 )! st(15) [63:0] $end
    $var wire 64 +! st(16) [63:0] $end
    $var wire 64 -! st(17) [63:0] $end
    $var wire 64 /! st(18) [63:0] $end
    $var wire 64 1! st(19) [63:0] $end
    $var wire 64 m st(2) [63:0] $end
    $var wire 64 3! st(20) [63:0] $end
    $var wire 64 5! st(21) [63:0] $end
    $var wire 64 7! st(22) [63:0] $end
    $var wire 64 9! st(23) [63:0] $end
    $var wire 64 ;! st(24) [63:0] $end
    $var wire 64 o st(3) [63:0] $end
    $var wire 64 q st(4) [63:0] $end
    $var wire 64 s st(5) [63:0] $end
    $var wire 64 u st(6) [63:0] $end
    $var wire 64 w st(7) [63:0] $end
    $var wire 64 y st(8) [63:0] $end
    $var wire 64 { st(9) [63:0] $end
    $var wire 64 =! stn(0) [63:0] $end
    $var wire 64 ?! stn(1) [63:0] $end
    $var wire 64 Q! stn(10) [63:0] $end
    $var wire 64 S! stn(11) [63:0] $end
    $var wire 64 U! stn(12) [63:0] $end
    $var wire 64 W! stn(13) [63:0] $end
    $var wire 64 Y! stn(14) [63:0] $end
    $var wire 64 [! stn(15) [63:0] $end
    $var wire 64 ]! stn(16) [63:0] $end
    $var wire 64 _! stn(17) [63:0] $end
    $var wire 64 a! stn(18) [63:0] $end
    $var wire 64 c! stn(19) [63:0] $end
    $var wire 64 A! stn(2) [63:0] $end
    $var wire 64 e! stn(20) [63:0] $end
    $var wire 64 g! stn(21) [63:0] $end
    $var wire 64 i! stn(22) [63:0] $end
    $var wire 64 k! stn(23) [63:0] $end
    $var wire 64 m! stn(24) [63:0] $end
    $var wire 64 C! stn(3) [63:0] $end
    $var wire 64 E! stn(4) [63:0] $end
    $var wire 64 G! stn(5) [63:0] $end
    $var wire 64 I! stn(6) [63:0] $end
    $var wire 64 K! stn(7) [63:0] $end
    $var wire 64 M! stn(8) [63:0] $end
    $var wire 64 O! stn(9) [63:0] $end
    $var wire 64 y! t [63:0] $end
    $var wire  1 # w $end
   $upscope $end
  $upscope $end
 $upscope $end
$enddefinitions $end


#0
0#
b1000000 $
b00000000000000000000000000000000 %
0&
0'
0(
1)
b00000000000000000000000000000000 *
b00000000000000000000000000000000 +
b00000000 ,
b000 -
b000 .
0/
b00000000 0
b00000000 1
b0000000000 2
03
b1111111 4
b00000000000000000000000000000101 5
b00000000000000000000000000011001 6
b0000000000000000000000000000000000000000000000000000000000000000 7
b0000000000000000000000000000000000000000000000000000000000000000 9
b0000000000000000000000000000000000000000000000000000000000000000 ;
b0000000000000000000000000000000000000000000000000000000000000000 =
b0000000000000000000000000000000000000000000000000000000000000000 ?
b0000000000000000000000000000000000000000000000000000000000000000 A
b0000000000000000000000000000000000000000000000000000000000000000 C
b0000000000000000000000000000000000000000000000000000000000000000 E
b0000000000000000000000000000000000000000000000000000000000000000 G
b0000000000000000000000000000000000000000000000000000000000000000 I
b0000000000000000000000000000000000000000000000000000000000000000 K
b0000000000000000000000000000000000000000000000000000000000000000 M
b0000000000000000000000000000000000000000000000000000000000000000 O
b0000000000000000000000000000000000000000000000000000000000000000 Q
b0000000000000000000000000000000000000000000000000000000000000000 S
b0000000000000000000000000000000000000000000000000000000000000000 U
b0000000000000000000000000000000000000000000000000000000000000000 W
b0000000000000000000000000000000000000000000000000000000000000000 Y
b0000000000000000000000000000000000000000000000000000000000000000 [
b0000000000000000000000000000000000000000000000000000000000000000 ]
b0000000000000000000000000000000000000000000000000000000000000000 _
b0000000000000000000000000000000000000000000000000000000000000000 a
b0000000000000000000000000000000000000000000000000000000000000000 c
b0000000000000000000000000000000000000000000000000000000000000000 e
b0000000000000000000000000000000000000000000000000000000000000000 g
b0000000000000000000000000000000000000000000000000000000000000000 i
b0000000000000000000000000000000000000000000000000000000000000000 k
b0000000000000000000000000000000000000000000000000000000000000000 m
b0000000000000000000000000000000000000000000000000000000000000000 o
b0000000000000000000000000000000000000000000000000000000000000000 q
b0000000000000000000000000000000000000000000000000000000000000000 s
b0000000000000000000000000000000000000000000000000000000000000000 u
b0000000000000000000000000000000000000000000000000000000000000000 w
b0000000000000000000000000000000000000000000000000000000000000000 y
b0000000000000000000000000000000000000000000000000000000000000000 {
b0000000000000000000000000000000000000000000000000000000000000000 }
b0000000000000000000000000000000000000000000000000000000000000000 !!
b0000000000000000000000000000000000000000000000000000000000000000 #!
b0000000000000000000000000000000000000000000000000000000000000000 %!
b0000000000000000000000000000000000000000000000000000000000000000 '!
b0000000000000000000000000000000000000000000000000000000000000000 )!
b0000000000000000000000000000000000000000000000000000000000000000 +!
b0000000000000000000000000000000000000000000000000000000000000000 -!
b0000000000000000000000000000000000000000000000000000000000000000 /!
b0000000000000000000000000000000000000000000000000000000000000000 1!
b0000000000000000000000000000000000000000000000000000000000000000 3!
b0000000000000000000000000000000000000000000000000000000000000000 5!
b0000000000000000000000000000000000000000000000000000000000000000 7!
b0000000000000000000000000000000000000000000000000000000000000000 9!
b0000000000000000000000000000000000000000000000000000000000000000 ;!
b0000000000000000000000000000000000000000000000000000000000000001 =!
b0000000000000000000000000000000000000000000000000000000000000000 ?!
b0000000000000000000000000000000000000000000000000000000000000000 A!
b0000000000000000000000000000000000000000000000000000000000000000 C!
b0000000000000000000000000000000000000000000000000000000000000000 E!
b0000000000000000000000000000000000000000000000000000000000000000 G!
b0000000000000000000000000000000000000000000000000000000000000000 I!
b0000000000000000000000000000000000000000000000000000000000000000 K!
b0000000000000000000000000000000000000000000000000000000000000000 M!
b0000000000000000000000000000000000000000000000000000000000000000 O!
b0000000000000000000000000000000000000000000000000000000000000000 Q!
b0000000000000000000000000000000000000000000000000000000000000000 S!
b0000000000000000000000000000000000000000000000000000000000000000 U!
b0000000000000000000000000000000000000000000000000000000000000000 W!
b0000000000000000000000000000000000000000000000000000000000000000 Y!
b0000000000000000000000000000000000000000000000000000000000000000 [!
b0000000000000000000000000000000000000000000000000000000000000000 ]!
b0000000000000000000000000000000000000000000000000000000000000000 _!
b0000000000000000000000000000000000000000000000000000000000000000 a!
b0000000000000000000000000000000000000000000000000000000000000000 c!
b0000000000000000000000000000000000000000000000000000000000000000 e!
b0000000000000000000000000000000000000000000000000000000000000000 g!
b0000000000000000000000000000000000000000000000000000000000000000 i!
b0000000000000000000000000000000000000000000000000000000000000000 k!
b0000000000000000000000000000000000000000000000000000000000000000 m!
b0000000000000000000000000000000000000000000000000000000000000000 o!
b0000000000000000000000000000000000000000000000000000000000000000 q!
b0000000000000000000000000000000000000000000000000000000000000000 s!
b0000000000000000000000000000000000000000000000000000000000000000 u!
b0000000000000000000000000000000000000000000000000000000000000000 w!
b0000000000000000000000000000000000000000000000000000000000000000 y!
b00000 {!
b00000000000000000000000000000000 |!
b000 }!
b00000000000000000000000000000000 ~!
b00000000000000000000000000000000 !"
b00000000000000000000000000000000 ""
1#"
1$"
b00000000000000000000000000000000 %"
b00000000 &"
b00000000 '"
0("
0)"
b00000000000000000000000000000000 *"
b00000000000000000000000000000000 +"
0,"
0-"
b0000000000 ."
b00101010 /"
b00000001 0"
b000 1"
b001 2"
b010 3"
b011 4"
b10111 5"
b000001000011000110001010001111010101011100100100101101110111000010001110011011101001111000001000011001101011111110010010100111111101010100101100 6"
b010100011101011100011001000011001011000001000101011100000100011111011110011011010110000010101000111010110010010011000001 ;"
b000000000000000000000000000000000000000000000000000000000000000100000000000000000000000000000000000000000000000010000000100000101000000000000000000000000000000000000000000000001000000010001010100000000000000000000000000000001000000000000000100000000000000000000000000000000000000000000000000000000000000010000000100010110000000000000000000000000000000010000000000000000000000000000001100000000000000000000000000000001000000000000000100000001000000110000000000000000000000000000000000000000000000010000000000010010000000000000000000000000000000000000000000000000000000010001010000000000000000000000000000000000000000000000000000000001000100000000000000000000000000000000000100000000000000010000000000010010000000000000000000000000000000010000000000000000000000000001010000000000000000000000000000000001000000000000000100000001000101110000000000000000000000000000000000000000000000000000000100010111000000000000000000000000000000000000000000000001000000010001001100000000000000000000000000000000000000000000000100000000000001110000000000000000000000000000000000000000000000010000000000000101000000000000000000000000000000000000000000000000000000010000000000000000000000000000000000000000000000000000000100000000000101010000000000000000000000000000000100000000000000000000000000010101000000000000000000000000000000010000000000000001000000010000001100000000000000000000000000000000000000000000000100000001000000000000000000000000000000000000000100000000000000000000000000000011000000000000000000000000000000010000000000000001000000000001000 ?"
#1
b00000000000000000000000000011001 5
b0000000000000000000000000000000000000000000000000000000000000000 =!
b11000 {!
0#"
0$"
#2
1#"
1$"
b00000010 &"
b0000000010 ."
#3
b001 }!
0#"
1("
#4
b1111111 $
b001 -
1#"
#5
0#"
0("
#6
1#
b0000000 $
b00000000000000000000000000000100 *
b001 .
b00000001 1
b0000000 4
b00110100001100110011001000110001 |!
b00000000000000000000000000011111 ~!
b00000000000000000000000000011111 ""
1#"
b00110100001100110011001000110001 %"
b00000000000000000000000000000100 +"
#7
0#"
#8
b0000001 $
b00000000000000000000000000001000 *
b00000010 1
b0000001 4
b0000000000000000000000000000000000110100001100110011001000110001 7
b00111000001101110011011000110101 |!
b00000000000000000000000000000000 ~!
b00000000000000000000000000000000 ""
1#"
b00111000001101110011011000110101 %"
b00000000000000000000000000001000 +"
#9
0#"
#10
b0000010 $
b00000000000000000000000000001100 *
b00000011 1
b0000010 4
b0011100000110111001101100011010100110100001100110011001000110001 7
b00110100001100110011001000110001 |!
1#"
b00110100001100110011001000110001 %"
b00000000000000000000000000001100 +"
#11
0#"
#12
b0000011 $
b00000000000000000000000000010000 *
b00000100 1
b0000011 4
b0000000000000000000000000000000000110100001100110011001000110001 9
b00111000001101110011011000110101 |!
1#"
b00111000001101110011011000110101 %"
b00000000000000000000000000010000 +"
#13
0#"
#14
b0000100 $
b00000000000000000000000000010100 *
b00000101 1
b0000100 4
b0011100000110111001101100011010100110100001100110011001000110001 9
b00110100001100110011001000110001 |!
1#"
b00110100001100110011001000110001 %"
b00000000000000000000000000010100 +"
#15
0#"
#16
b0000101 $
b00000000000000000000000000011000 *
b00000110 1
b0000101 4
b0000000000000000000000000000000000110100001100110011001000110001 ;
b00111000001101110011011000110101 |!
1#"
b00111000001101110011011000110101 %"
b00000000000000000000000000011000 +"
#17
0#"
#18
b0000110 $
b00000000000000000000000000011100 *
b00000111 1
b0000110 4
b0011100000110111001101100011010100110100001100110011001000110001 ;
b00110100001100110011001000110001 |!
1#"
b00110100001100110011001000110001 %"
b00000000000000000000000000011100 +"
#19
0#"
#20
b0000111 $
b00000000000000000000000000100000 *
b00001000 1
b0000111 4
b0000000000000000000000000000000000110100001100110011001000110001 =
b00111000001101110011011000110101 |!
1#"
b00111000001101110011011000110101 %"
b00000000000000000000000000100000 +"
#21
0#"
#22
b0001000 $
b00000000000000000000000000100100 *
b00001001 1
b0001000 4
b0011100000110111001101100011010100110100001100110011001000110001 =
b00110100001100110011001000110001 |!
1#"
b00110100001100110011001000110001 %"
b00000000000000000000000000100100 +"
#23
0#"
#24
b0001001 $
b00000000000000000000000000101000 *
b00001010 1
b0001001 4
b0000000000000000000000000000000000110100001100110011001000110001 ?
b00111000001101110011011000110101 |!
1#"
b00111000001101110011011000110101 %"
b00000000000000000000000000101000 +"
#25
0#"
#26
b0001010 $
b00000000000000000000000000101100 *
b00001011 1
b0001010 4
b0011100000110111001101100011010100110100001100110011001000110001 ?
b00110100001100110011001000110001 |!
1#"
b00110100001100110011001000110001 %"
b00000000000000000000000000101100 +"
#27
0#"
#28
b0001011 $
b00000000000000000000000000110000 *
b00001100 1
b0001011 4
b0000000000000000000000000000000000110100001100110011001000110001 A
b00111000001101110011011000110101 |!
1#"
b00111000001101110011011000110101 %"
b00000000000000000000000000110000 +"
